Workbook

Sheet README & Legend
A1: Cytognosis Foundation — Funding & Opportunity Funnel
A2: Master data workbook · compiled 2026-05-30 · companion to Funding_Strategy_Master_2026-05-30.md
A5: HOW THIS WORKBOOK IS ORGANIZED
A6: Master — Funding Opportunities | B6: All scored funding/grant/accelerator/credit candidates that passed the eligibility gate, with the full metric schema.
A7: Meta-Sources | B7: The discovery/monitoring layer (portals, aggregators, newsletters) used to FIND opportunities and to power the weekly scraper. Not funders themselves.
A8: PAC & Advocacy | B8: Companion list of Patient Advocacy Council / partnership targets. OneMind is cross-listed here and in Master (funder+accelerator+PAC).
A9: Backup & Parked | B9: Promising-but-blocked or missing-data candidates: invitation-only, tenured-PI-only, partner-institution-only, for-profit/VC (PBC-phase), or unverifiable. Kept visible, clearly marked.
A10: Wave Action Plan | B10: Chronological do-list grouped by wave with the single next action and deadline for each priority target.
A12: THE FUNNEL (hierarchical, iterative filtering)
A13: Level 0 — Universe | B13: Widest net: existing 71 Monday entries + 6 research clusters + discovered adjacents (~150 raw).
A14: Level 1 — Eligibility gate | B14: Hard binary filters. E1 entity fit (nonprofit-eligible / clean PBC-path / partner). E2 stage fit (early/pre-seed/Day-1 OK; not revenue/tenure/invite-only-with-no-path). E3 geography (US or US-path). Result: PASS / BACKUP / EXCLUDE.
A15: Level 2 — Alignment & values score | B15: Four 0–5 axes -> composite FitScore 0–10 (formula). Advance if FitScore >= 6.0; 4.0–5.9 = monitor/opportunistic; < 4.0 = deprioritize.
A16: Level 3 — Opportunity economics | B16: For survivors: funding scale bucket, amounts, current status, process timeline, review mechanism.
A17: Level 4 — Wave assignment | B17: Combine fit x economics x deadline urgency x effort into Waves 0–3 (timing strategy).
A18: Backup rule | B18: Any promising candidate where a gate fails OR a key metric can't be verified is parked in Backup with the reason — never silently dropped.
A20: SCORING RUBRIC (0–5 each; FitScore is a formula)
A21: AI (col J) | B21: 5 = AI/ML is the core lens · 4 = major · 3 = one of several · 2 = minor/enabling · 1 = incidental · 0 = none
A22: Health/MH (col K) | B22: 5 = mental-health / precision-psychiatry core · 4 = health core · 3 = health-adjacent/biomedical · 2 = health among many · 1 = tangential · 0 = none
A23: Values (col L) | B23: Count of strong matches among {moonshot/Pasteur, open-science, mission/impact-driven, collaborative/consortia}, 0–5
A24: Stage-fit (col M) | B24: 5 = built for early/Day-1/pre-seed or FRO-style · 4 = nonprofit/early friendly · 3 = nonprofit-eligible but expects maturity/partner · 2 = needs faculty/partner or for-profit · 1 = tenured/invite-only · 0 = ineligible
A25: FitScore (col N) | B25: Formula: K/5×3 + L/5×2.5 + J/5×2 + M/5×2.5 (max 10). Health & Stage weighted highest, then Values, then AI.
A27: FUNDING SCALE BUCKETS (col R, from Typical $)
A28: Small | B28: <= $250K
A29: Medium | B29: $250K – $1.5M
A30: Large | B30: $1.5M – $10M
A31: Mega | B31: > $10M
A32: (n/a) | B32: Amount not yet verified — see Backup/notes
A34: WAVES (col X)
A35: Wave 0 — Now (≤4 wks) | B35: Imminent open deadlines with FitScore≥6 + zero-cost prerequisites (registrations, free credits, HBNet, FRO submission).
A36: Wave 1 — 1–3 months | B36: High-fit near-term deadlines and high-value rolling targets to start now.
A37: Wave 2 — 3–6 months | B37: Fall cycles & relationship-build-now/apply-later; recurring annual programs.
A38: Wave 3 — 6–18 months / PBC | B38: Large strategic processes, EU/intl consortia, and for-profit/PBC-contingent (SBIR, accelerators taking equity).
A40: DATA CONFIDENCE (col AE)
A41: High | B41: Verified on a live primary source on/around 2026-05-30.
A42: Med | B42: From a credible secondary source or partially confirmed; re-verify before acting.
A43: Low | B43: Unconfirmed / page didn't load / inferred — treat as a lead, verify first.
A45: REGISTRY (col AF) | B45: Existing = already on Monday Funding Opportunities board · Refresh = on board but status updated here · New = net-new this pass.
A46: Prior Status (col AG) | B46: Real application history: Applied-rejected / In progress / Alumnus-WARM / Not started / Planned / Missed.
A47: Access / Warm-Intro Path (col AH) | B47: The named person/relationship that opens the door — see the Network & Warm-Intro Map tab. 'WARM' = an existing relationship to activate.
A49: ITERATION LOG
A50: v3 — 2026-05-30 | B50: Status corrections + international strategy: SAM.gov DONE; NVIDIA Inception auto-rejected (nonprofit/form mismatch — warm program-lead contact; pivot to NVIDIA Academic Grant); ARPA-H = pick ONE MO ISO → HSF chosen (PHO = alternative); Wellcome Leap HBNet emailed Dec+Jan, NO RESPONSE → escalate via member institution / Program Director. Deepened EU Horizon Cluster 1 (US = self-funded Associated Partner; UK associated since 2024 → anchor via Manchester/Madhvi). +2 rows: UKRI/MRC via Madhvi's Future Leaders Fellowship (F090), EU EP PerMed personalised-medicine partnership (F091). Added Madhvi Menon to the Network tab.
A51: v2 — 2026-05-30 | B51: Added Prior Status + Access/Warm-Intro Path columns and a Network & Warm-Intro Map tab. +24 rows: Eli Lilly (LRAP, LPRC, Catalyze360, Grant Office), Nucleate×Lilly Grand Challenge + Nucleate Activator (alumnus), Mayo Accelerate/Orchestrate, BRAIN Foundation, SPARK for Autism, SPARK NS, Autism Society/SFASA, Mental Research Institute, MGH Center for Digital Mental Health, APA App-Evaluation/Council/Future-DSM, APA Foundation, American Psychological Association APA Labs, Mt Sinai-Roussos + MGH-Smoller academic partners, and YC/Foresight/QB3 application history. PAC tab +6 (autism cluster, Center for Digital MH, MRI, Sarika connector).
A52: v1 — 2026-05-30 | B52: Initial funnel: 65 scored funding rows, 30 meta-sources, 20 PAC orgs, backup list, wave plan.

Sheet Master — Funding Opportunities
A1: Master — Funding Opportunities (funnel-scored)
A2: FitScore is a live formula (col N). Scale Bucket is a live formula (col R). Sort/filter freely. See README & Legend.
A4: ID | B4: Opportunity (Org — Program) | C4: Funder Org | D4: Source Type | E4: Opportunity Type | F4: Instrument | G4: Eligibility (Nonprofit/Early) | H4: Geo | I4: L1 Gate | J4: AI | K4: Health/MH | L4: Values | M4: Stage-fit | N4: FitScore (0-10) | O4: Amount Min $ | P4: Amount Max $ | Q4: Amount Typical $ | R4: Scale Bucket | S4: Status | T4: Next Deadline / Window | U4: Deadline Type | V4: Process & Timeline | W4: Review | X4: Wave | Y4: Strategic Pairing | Z4: Insider / Access Path | AA4: Apply URL | AB4: Monitor / Opportunities URL | AC4: Feed Type | AD4: Mission Rationale | AE4: Data Conf. | AF4: Registry | AG4: Prior Status | AH4: Access / Warm-Intro Path
A5: F001 | B5: ARPA-H IGoR (AI mechanistic disease modeling) | C5: ARPA-H | D5: Government | E5: Program ISO | F5: grant (OT) | G5: Yes | H5: US | I5: PASS | J5: 5 | K5: 4 | L5: 4 | M5: 5 | N5: =ROUND(K5/5*3+L5/5*2.5+J5/5*2+M5/5*2.5,1) -> 8.9 | R5: =IF(Q5="","(n/a)",IF(Q5<=250000,"Small",IF(Q5<=1500000,"Medium",IF(Q5<=10000000,"Large","Mega")))) -> (n/a) | S5: Open | T5: Solution Summary 2026-06-25; full 2026-08-06 | U5: Single | V5: SS→encourage→full; 5yr/3-phase; AI-assisted triage | W5: program-officer | X5: 0 | Y5: ARPA-H PHO/HSF ISO | Z5: ARPANET-H hubs; ARPA-H Vitals | AA5: https://arpa-h.gov/explore-funding/programs/igor | AB5: https://arpa-h.gov/explore-funding/open-funding-opportunities | AC5: API(Grants.gov)+HTML | AD5: AI-powered multiscale mechanistic disease modeling = Cytoverse | AE5: High | AF5: New | AG5: Not started | AH5: ARPA-H Vitals; Ananth Grama federal network
A6: F002 | B6: NIMH BRAIN: Next-Gen Human Sensor Tech (RFA-MH-26-140, U01) | C6: NIH / NIMH | D6: Government | E6: Cooperative agreement | F6: grant | G6: Yes | H6: US | I6: PASS | J6: 4 | K6: 5 | L6: 4 | M6: 4 | N6: =ROUND(K6/5*3+L6/5*2.5+J6/5*2+M6/5*2.5,1) -> 8.6 | O6: 1000000 | P6: 2000000 | Q6: 1800000 | R6: =IF(Q6="","(n/a)",IF(Q6<=250000,"Small",IF(Q6<=1500000,"Medium",IF(Q6<=10000000,"Large","Mega")))) -> Large | S6: Open | T6: 2026-06-15 (recurs to 2027-06-15) | U6: Recurring | V6: 8-12wk prep; submit→review Nov→council Jan→start Apr | W6: peer_review | X6: 0 | Y6: NIMH R21; ARPA-H IGoR | Z6: BRAIN Initiative Alliance | AA6: https://grants.nih.gov/grants/guide/rfa-files/RFA-MH-26-140.html | AB6: https://braininitiative.nih.gov/funding/funding-opportunities | AC6: RSS(NIH Guide) | AD6: Optical/NIRS wearable, brain-behavior sync = exact Cytoscope | AE6: High | AF6: New
A7: F003 | B7: AWS Imagine Grant — Pathfinder (GenAI) | C7: Amazon Web Services | D7: Corporate | E7: Corporate grant | F7: grant+credits | G7: Yes | H7: US | I7: PASS | J7: 5 | K7: 3 | L7: 3 | M7: 4 | N7: =ROUND(K7/5*3+L7/5*2.5+J7/5*2+M7/5*2.5,1) -> 7.3 | O7: 100000 | P7: 300000 | Q7: 300000 | R7: =IF(Q7="","(n/a)",IF(Q7<=250000,"Small",IF(Q7<=1500000,"Medium",IF(Q7<=10000000,"Large","Mega")))) -> Medium | S7: Open | T7: Round 1 2026-06-05; R2 invite 07-14; award Dec | U7: Recurring | V7: 3-4wk prep; R1 Jun5→R2 Sep14→award Dec | W7: program-officer | X7: 0 | Y7: AWS Activate; NVIDIA | Z7: AWS Gen AI Innovation Center | AA7: https://apply.younoodle.com/showcase/competition/2026_aws_imagine_grant | AB7: https://aws.amazon.com/government-education/nonprofits/aws-imagine-grant-program/ | AC7: HTML | AD7: Edge/agentic AI biosensor+navigator = Pathfinder criteria | AE7: High | AF7: Refresh
A8: F004 | B8: NSF X-Labs — Topic 1 Sensing & Imaging (Phase 0) | C8: NSF (TIP) | D8: Government | E8: Other Transaction | F8: grant (OT) | G8: Yes | H8: US | I8: PASS | J8: 4 | K8: 3 | L8: 4 | M8: 5 | N8: =ROUND(K8/5*3+L8/5*2.5+J8/5*2+M8/5*2.5,1) -> 7.9 | O8: 1500000 | P8: 50000000 | Q8: 15000000 | R8: =IF(Q8="","(n/a)",IF(Q8<=250000,"Small",IF(Q8<=1500000,"Medium",IF(Q8<=10000000,"Large","Mega")))) -> Mega | S8: Open | T8: Offers due 2026-07-13 (solic. open to 2028) | U8: Single | V8: Phase0 ≤$1.5M/9-12mo→Phase1 ≤$50M/yr; dedicated team | W8: expert_committee | X8: 0 | Y8: Convergent Research FRO | Z8: Hervé Marie-Nelly co-submission | AA8: https://sam.gov/workspace/contract/opp/0da4e39df20f481ca9299b0edefe23d2/view | AB8: https://www.nsf.gov/funding/initiatives/nsf-x-labs | AC8: API(SAM.gov)+RSS | AD8: Adaptive fNIRS spectroscopy headset = Sensing&Imaging exact | AE8: High | AF8: Refresh | AG8: In progress | AH8: Joint submission w/ Hervé Marie-Nelly (ex-insitro)
A9: F005 | B9: Wellcome Leap — Health Breakthrough Network (HBNet) membership | C9: Wellcome Leap | D9: FRO / Moonshot | E9: Network access | F9: in-kind | G9: Yes | H9: Intl/US | I9: PASS | J9: 0 | K9: 0 | L9: 5 | M9: 5 | N9: =ROUND(K9/5*3+L9/5*2.5+J9/5*2+M9/5*2.5,1) -> 5 | R9: =IF(Q9="","(n/a)",IF(Q9<=250000,"Small",IF(Q9<=1500000,"Medium",IF(Q9<=10000000,"Large","Mega")))) -> (n/a) | S9: Rolling | T9: Always open (do now) | U9: Rolling | V9: Email HBNet@wellcomeleap.org; sign MARFA/CORFA | W9: internal_panel | X9: 0 | Y9: All Wellcome Leap programs | Z9: HBNet@wellcomeleap.org | AA9: https://wellcomeleap.org/wellcome-leap-hbnet/ | AB9: https://wellcomeleap.org/ | AC9: Newsletter | AD9: Free prerequisite that unlocks every Leap program | AE9: High | AF9: New | AG9: Emailed HBNet Dec 15 2025 + reminder Jan 26 2026 — NO RESPONSE | AH9: Escalate: via an HBNet member institution (Manchester/Madhvi?, McLean, Mt Sinai) or a Program Director (e.g., Susanne Ahmari/MCPsych); the shared inbox is unresponsive
A10: F006 | B10: Convergent Research — FRO idea submission | C10: Convergent Research | D10: FRO / Moonshot | E10: FRO incubation | F10: grant (match) | G10: Yes | H10: US/UK | I10: PASS | J10: 4 | K10: 4 | L10: 5 | M10: 5 | N10: =ROUND(K10/5*3+L10/5*2.5+J10/5*2+M10/5*2.5,1) -> 9 | O10: 10000000 | P10: 50000000 | Q10: 25000000 | R10: =IF(Q10="","(n/a)",IF(Q10<=250000,"Small",IF(Q10<=1500000,"Medium",IF(Q10<=10000000,"Large","Mega")))) -> Mega | S10: Rolling | T10: Always open (no deadline) | U10: Rolling | V10: Abstract→eval→funder match→incubate (6-18mo) | W10: internal_panel | X10: 0 | Y10: NSF X-Labs; Schmidt/Astera | Z10: Adam Marblestone network; FAS.org | AA10: https://noteforms.com/forms/fro-abstract-submissions-uyswk3 | AB10: https://www.convergentresearch.org/get-involved | AC10: Newsletter | AD10: Open Cytoverse atlas is textbook FRO; $10M+ anchor | AE10: High | AF10: Refresh | AG10: Not started | AH10: Adam Marblestone / FAS FRO network
A11: F007 | B11: Anthropic — AI for Science (Claude credits) | C11: Anthropic | D11: Corporate | E11: Compute credits | F11: credits | G11: Yes | H11: Intl | I11: PASS | J11: 5 | K11: 4 | L11: 4 | M11: 5 | N11: =ROUND(K11/5*3+L11/5*2.5+J11/5*2+M11/5*2.5,1) -> 8.9 | O11: 20000 | P11: 50000 | Q11: 30000 | R11: =IF(Q11="","(n/a)",IF(Q11<=250000,"Small",IF(Q11<=1500000,"Medium",IF(Q11<=10000000,"Large","Mega")))) -> Small | S11: Rolling | T11: Monthly (1st Monday) | U11: Rolling | V11: 2-4wk; monthly decision; 6-mo credit validity | W11: program-officer | X11: 0 | Y11: Cohere; NAIRR | Z11: Claude for Nonprofits (already granted) | AA11: https://www.anthropic.com/news/ai-for-science-program | AB11: https://www.anthropic.com/news/ai-for-science-program | AC11: HTML | AD11: Low-friction credits for Cytoverse FM + Cytonome | AE11: High | AF11: Refresh
A12: F008 | B12: NAIRR Pilot — GPU compute allocation | C12: NSF / NAIRR | D12: Government | E12: Compute access | F12: in-kind | G12: Yes | H12: US | I12: PASS | J12: 5 | K12: 3 | L12: 4 | M12: 4 | N12: =ROUND(K12/5*3+L12/5*2.5+J12/5*2+M12/5*2.5,1) -> 7.8 | R12: =IF(Q12="","(n/a)",IF(Q12<=250000,"Small",IF(Q12<=1500000,"Medium",IF(Q12<=10000000,"Large","Mega")))) -> (n/a) | S12: Rolling | T12: Quarterly review cycles | U12: Rolling | V12: Apply→quarterly allocation; DOE-lab GPU time | W12: internal_panel | X12: 0 | Y12: Anthropic; Lambda | Z12: — | AA12: https://nairrpilot.org/opportunities/allocations | AB12: https://nairrpilot.org/opportunities | AC12: HTML | AD12: Cleanest nonprofit path to large GPU for Cytoverse training | AE12: High | AF12: New
A13: F009 | B13: ARPA-H — Proactive Health Office (PHO) ISO | C13: ARPA-H | D13: Government | E13: Mission Office ISO | F13: grant (OT) | G13: Yes | H13: US | I13: PASS | J13: 2 | K13: 5 | L13: 4 | M13: 5 | N13: =ROUND(K13/5*3+L13/5*2.5+J13/5*2+M13/5*2.5,1) -> 8.3 | O13: 2000000 | P13: 20000000 | Q13: 5000000 | R13: =IF(Q13="","(n/a)",IF(Q13<=250000,"Small",IF(Q13<=1500000,"Medium",IF(Q13<=10000000,"Large","Mega")))) -> Large | S13: Rolling | T13: Solution Summaries rolling to 2029-03-05 | U13: Rolling | V13: SS→~4.5mo encourage→45d full→~8-9mo cash | W13: program-officer | X13: 1 | Y13: ARPA-H IGoR; DELPHI | Z13: ARPA-H Vitals; PHO PM office | AA13: https://sam.gov/opp/a5b72db5139040f8b2a1dcc2d2c96733/view | AB13: https://arpa-h.gov/explore-funding/open-funding-opportunities | AC13: API(SAM.gov) | AD13: 'Prevent people becoming patients' = proactive health mission | AE13: High | AF13: Refresh | AG13: Not started | AH13: ARPA-H Vitals; Ananth Grama
A14: F010 | B14: ARPA-H — Health Science Futures (HSF) ISO | C14: ARPA-H | D14: Government | E14: Mission Office ISO | F14: grant (OT) | G14: Yes | H14: US | I14: PASS | J14: 4 | K14: 4 | L14: 4 | M14: 5 | N14: =ROUND(K14/5*3+L14/5*2.5+J14/5*2+M14/5*2.5,1) -> 8.5 | O14: 2000000 | P14: 20000000 | Q14: 5000000 | R14: =IF(Q14="","(n/a)",IF(Q14<=250000,"Small",IF(Q14<=1500000,"Medium",IF(Q14<=10000000,"Large","Mega")))) -> Large | S14: Rolling | T14: Rolling to 2029-03-05 | U14: Rolling | V14: SS→encourage→full; ~8-9mo to cash | W14: program-officer | X14: 1 | Y14: ARPA-H PHO; IGoR | Z14: ARPA-H Vitals | AA14: https://sam.gov/opp/29c3ac2ea6754d1f897f9c71204c0eea/view | AB14: https://arpa-h.gov/explore-funding/open-funding-opportunities | AC14: API(SAM.gov) | AD14: AI×biology + multi-scale modeling = Cytoverse | AE14: High | AF14: Refresh | AG14: Not started | AH14: ARPA-H Vitals
A15: F011 | B15: NIMH — Parent R21 (computational psychiatry pilot) | C15: NIH / NIMH | D15: Government | E15: R-series grant | F15: grant | G15: Yes | H15: US | I15: PASS | J15: 4 | K15: 5 | L15: 4 | M15: 4 | N15: =ROUND(K15/5*3+L15/5*2.5+J15/5*2+M15/5*2.5,1) -> 8.6 | O15: 200000 | P15: 275000 | Q15: 275000 | R15: =IF(Q15="","(n/a)",IF(Q15<=250000,"Small",IF(Q15<=1500000,"Medium",IF(Q15<=10000000,"Large","Mega")))) -> Medium | S15: Rolling | T15: Std dates Feb/Jun/Oct | U15: Recurring | V15: ~9-12mo submit→award; 2yr / ≤$275K | W15: peer_review | X15: 1 | Y15: NIMH U01/R34 | Z15: NIMH program officer (DTR) | AA15: https://grants.nih.gov/funding/activity-codes/R21 | AB15: https://grants.nih.gov/grants/guide | AC15: RSS(NIH Guide) | AD15: Ideal first NIH grant: biotyping/biomarker pilot | AE15: High | AF15: New
A16: F012 | B16: NIMH BRAIN: Data Archives (RFA-MH-25-110, R24) | C16: NIH / NIMH | D16: Government | E16: R24 grant | F16: grant | G16: Yes | H16: US | I16: PASS | J16: 3 | K16: 5 | L16: 5 | M16: 4 | N16: =ROUND(K16/5*3+L16/5*2.5+J16/5*2+M16/5*2.5,1) -> 8.7 | R16: =IF(Q16="","(n/a)",IF(Q16<=250000,"Small",IF(Q16<=1500000,"Medium",IF(Q16<=10000000,"Large","Mega")))) -> (n/a) | S16: Open | T16: through 2026-06-25 | U16: Recurring | V16: Std NIH timeline | W16: peer_review | X16: 1 | Y16: Cytoverse open data | Z16: BRAIN Alliance | AA16: https://grants.nih.gov/grants/guide/rfa-files/RFA-MH-25-110.html | AB16: https://braininitiative.nih.gov/funding/funding-opportunities | AC16: RSS(NIH Guide) | AD16: Funds Cytoverse as open FAIR psychiatric data archive | AE16: Med | AF16: New
A17: F013 | B17: NIMH BRAIN: Health-Equity Tech Partnerships (RFA-NS-25-016, R34) | C17: NIH / NIMH | D17: Government | E17: R34 planning grant | F17: grant | G17: Yes | H17: US | I17: PASS | J17: 3 | K17: 5 | L17: 5 | M17: 4 | N17: =ROUND(K17/5*3+L17/5*2.5+J17/5*2+M17/5*2.5,1) -> 8.7 | Q17: 450000 | R17: =IF(Q17="","(n/a)",IF(Q17<=250000,"Small",IF(Q17<=1500000,"Medium",IF(Q17<=10000000,"Large","Mega")))) -> Medium | S17: Open | T17: through 2026-06-18 | U17: Recurring | V17: Planning grant ~2-3yr | W17: peer_review | X17: 1 | Y17: NIMH U01 | Z17: BRAIN Alliance | AA17: https://grants.nih.gov/grants/guide/rfa-files/RFA-NS-25-016.html | AB17: https://braininitiative.nih.gov/funding/funding-opportunities | AC17: RSS(NIH Guide) | AD17: Brain-tech + underserved communities framing | AE17: Med | AF17: New
A18: F014 | B18: Convergent Research / Renaissance — Emergent Ventures (bridge) | C18: Mercatus Center | D18: EA / Longtermist | E18: Micro-grant | F18: grant | G18: Yes | H18: Intl | I18: PASS | J18: 3 | K18: 3 | L18: 4 | M18: 5 | N18: =ROUND(K18/5*3+L18/5*2.5+J18/5*2+M18/5*2.5,1) -> 7.5 | O18: 10000 | P18: 50000 | Q18: 30000 | R18: =IF(Q18="","(n/a)",IF(Q18<=250000,"Small",IF(Q18<=1500000,"Medium",IF(Q18<=10000000,"Large","Mega")))) -> Small | S18: Rolling | T18: Rolling (~7-day turnaround) | U18: Rolling | V18: Email pitch→days-weeks | W18: program-officer | X18: 1 | Y18: Manifund; SFF | Z18: Tyler Cowen | AA18: https://www.mercatus.org/emergent-ventures | AB18: https://www.mercatus.org/emergent-ventures | AC18: HTML | AD18: Fast non-dilutive bridge + credibility for moonshot | AE18: High | AF18: Refresh
A19: F015 | B19: Patrick J. McGovern Foundation — Data Practice Accelerator | C19: Patrick J. McGovern Foundation | D19: Philanthropic | E19: Capacity grant | F19: grant | G19: Yes | H19: US/Intl | I19: PASS | J19: 4 | K19: 3 | L19: 4 | M19: 4 | N19: =ROUND(K19/5*3+L19/5*2.5+J19/5*2+M19/5*2.5,1) -> 7.4 | P19: 125000 | Q19: 125000 | R19: =IF(Q19="","(n/a)",IF(Q19<=250000,"Small",IF(Q19<=1500000,"Medium",IF(Q19<=10000000,"Large","Mega")))) -> Small | S19: Open | T19: ~2026-07-01 (rolling cohorts) | U19: Recurring | V19: Rolling EOI→cohort; ≤$125K + in-kind | W19: program-officer | X19: 1 | Y19: — | Z19: PJMF program officers | AA19: https://www.mcgovern.org/grants/ | AB19: https://www.mcgovern.org | AC19: HTML | AD19: AI-for-public-good data org; starter capital + capacity | AE19: Med | AF19: New
A20: F016 | B20: NVIDIA — Academic Grant Program (GPU hardware) | C20: NVIDIA | D20: Corporate | E20: Hardware grant | F20: in-kind | G20: Yes | H20: Intl | I20: PASS | J20: 5 | K20: 3 | L20: 3 | M20: 4 | N20: =ROUND(K20/5*3+L20/5*2.5+J20/5*2+M20/5*2.5,1) -> 7.3 | O20: 10000 | P20: 100000 | Q20: 50000 | R20: =IF(Q20="","(n/a)",IF(Q20<=250000,"Small",IF(Q20<=1500000,"Medium",IF(Q20<=10000000,"Large","Mega")))) -> Small | S20: Rolling | T20: Always open | U20: Rolling | V20: Apply→4-8wk review | W20: internal_panel | X20: 1 | Y20: NAIRR; Lambda | Z20: NVIDIA Inception | AA20: https://academicgrants.nvidia.com/academicgrantprogram/s/Application | AB20: https://www.nvidia.com/en-us/industries/higher-education-research/academic-grant-program/ | AC20: HTML | AD20: H100-class hardware for Cytoverse training + edge inference | AE20: High | AF20: New
A21: F017 | B21: Cohere Labs — Catalyst Grants (credits) | C21: Cohere | D21: Corporate | E21: Compute credits | F21: credits | G21: Yes | H21: Intl | I21: PASS | J21: 5 | K21: 3 | L21: 4 | M21: 4 | N21: =ROUND(K21/5*3+L21/5*2.5+J21/5*2+M21/5*2.5,1) -> 7.8 | R21: =IF(Q21="","(n/a)",IF(Q21<=250000,"Small",IF(Q21<=1500000,"Medium",IF(Q21<=10000000,"Large","Mega")))) -> (n/a) | S21: Rolling | T21: Always open | U21: Rolling | V21: Apply→rolling review; email labs@cohere.com | W21: internal_panel | X21: 1 | Y21: Anthropic AI for Science | Z21: — | AA21: https://cohere.com/research/grants/application | AB21: https://cohere.com/research/grants | AC21: HTML | AD21: Healthcare is explicit focus; on-device Cytonome fit | AE21: High | AF21: New
A22: F018 | B22: Microsoft — AI for Health (credits + collaboration) | C22: Microsoft | D22: Corporate | E22: Credits + collab | F22: in-kind | G22: Yes | H22: Intl | I22: PASS | J22: 5 | K22: 4 | L22: 4 | M22: 4 | N22: =ROUND(K22/5*3+L22/5*2.5+J22/5*2+M22/5*2.5,1) -> 8.4 | R22: =IF(Q22="","(n/a)",IF(Q22<=250000,"Small",IF(Q22<=1500000,"Medium",IF(Q22<=10000000,"Large","Mega")))) -> (n/a) | S22: Rolling | T22: Always open | U22: Rolling | V22: Apply→rolling team response | W22: program-officer | X22: 1 | Y22: Founders Hub (PBC) | Z22: MSR AI for Good Lab | AA22: https://www.microsoft.com/en-us/research/project/ai-for-health/ | AB22: https://www.microsoft.com/en-us/research/group/ai-for-good-research-lab/ | AC22: HTML | AD22: AI×health Azure credits + researcher collaboration | AE22: Med | AF22: New
A23: F019 | B23: OneMind — Rising Star Award | C23: One Mind | D23: Mental-Health Foundation | E23: Research grant | F23: grant | G23: Partner-only (faculty-equiv host) | H23: US | I23: BACKUP | J23: 4 | K23: 5 | L23: 5 | M23: 3 | N23: =ROUND(K23/5*3+L23/5*2.5+J23/5*2+M23/5*2.5,1) -> 8.6 | O23: 300000 | P23: 300000 | Q23: 300000 | R23: =IF(Q23="","(n/a)",IF(Q23<=250000,"Small",IF(Q23<=1500000,"Medium",IF(Q23<=10000000,"Large","Mega")))) -> Medium | S23: Watch | T23: Annual Feb–Apr (2026 closed 04-27) | U23: Recurring | V23: ~6-8wk; submit→Jul decision→Jan funds; 3yr/$300K | W23: expert_committee | X23: 2 | Y23: OneMind Accelerator/OMLEC | Z23: CSO Tahilia Rebello; OMLEC | AA23: https://onemind.org/what-we-do/one-mind-rising-star-academy/one-mind-rising-star-awards/ | AB23: https://onemind.org/ | AC23: HTML | AD23: Transdiagnostic precision psychiatry + AI biomarkers; needs academic-affiliated PI | AE23: High | AF23: New | AG23: Not started — needs academic-host PI | AH23: OneMind CSO Tahilia Rebello; OMLEC
A24: F020 | B24: Google.org — AI for Science Impact Challenge | C24: Google.org | D24: Corporate | E24: Grant + accelerator | F24: grant | G24: Yes | H24: Intl/US | I24: PASS | J24: 5 | K24: 4 | L24: 5 | M24: 4 | N24: =ROUND(K24/5*3+L24/5*2.5+J24/5*2+M24/5*2.5,1) -> 8.9 | O24: 500000 | P24: 3000000 | Q24: 1500000 | R24: =IF(Q24="","(n/a)",IF(Q24<=250000,"Small",IF(Q24<=1500000,"Medium",IF(Q24<=10000000,"Large","Mega")))) -> Medium | S24: Closed-next | T24: ~Q1 2027 (cycle just closed 05-01) | U24: Recurring | V24: 6-8wk prep; submit→~4mo decision | W24: program-officer | X24: 2 | Y24: Google GenAI Accelerator | Z24: — | AA24: https://www.google.org/impact-challenges/ai-science/ | AB24: https://blog.google/outreach-initiatives/google-org/ | AC24: HTML | AD24: 'GPS for biology' + open-source mandate = near-exact | AE24: High | AF24: Refresh
A25: F021 | B25: OpenAI Foundation — Life Sciences & Curing Diseases | C25: OpenAI Foundation | D25: Corporate | E25: Grant (cash) | F25: grant | G25: Path/nonprofit | H25: US | I25: PASS | J25: 5 | K25: 4 | L25: 4 | M25: 4 | N25: =ROUND(K25/5*3+L25/5*2.5+J25/5*2+M25/5*2.5,1) -> 8.4 | R25: =IF(Q25="","(n/a)",IF(Q25<=250000,"Small",IF(Q25<=1500000,"Medium",IF(Q25<=10000000,"Large","Mega")))) -> (n/a) | S25: Watch | T25: Mechanism expected H2 2026 | U25: Single | V25: Submit interest now; RFP forthcoming | W25: program-officer | X25: 2 | Y25: OpenAI MH grants | Z25: Jacob Trefethen (lead) | AA25: https://openaifoundation.org | AB25: https://openaifoundation.org | AC25: Newsletter | AD25: $1B program; neuro/Alzheimer's + open health data | AE25: Med | AF25: New
A26: F022 | B26: OpenAI — AI & Mental Health Research Grants | C26: OpenAI | D26: Corporate | E26: Research grant | F26: grant | G26: Yes | H26: Intl | I26: PASS | J26: 5 | K26: 5 | L26: 4 | M26: 4 | N26: =ROUND(K26/5*3+L26/5*2.5+J26/5*2+M26/5*2.5,1) -> 9 | O26: 5000 | P26: 100000 | Q26: 75000 | R26: =IF(Q26="","(n/a)",IF(Q26<=250000,"Small",IF(Q26<=1500000,"Medium",IF(Q26<=10000000,"Large","Mega")))) -> Small | S26: Watch | T26: ~Q4 2026 (closed Dec 2025) | U26: Recurring | V26: ~6wk; Jan decision | W26: program-officer | X26: 2 | Y26: OpenAI Foundation LS | Z26: — | AA26: https://openai.com/index/ai-mental-health-research-grants/ | AB26: https://openai.smapply.org | AC26: HTML | AD26: Direct AI × mental health; high signal, small $ | AE26: High | AF26: New
A27: F023 | B27: CZI Science — AI/GPU Compute RFA | C27: Chan Zuckerberg Initiative | D27: Philanthropic | E27: Compute (in-kind) | F27: in-kind | G27: Yes | H27: US | I27: PASS | J27: 5 | K27: 4 | L27: 5 | M27: 4 | N27: =ROUND(K27/5*3+L27/5*2.5+J27/5*2+M27/5*2.5,1) -> 8.9 | R27: =IF(Q27="","(n/a)",IF(Q27<=250000,"Small",IF(Q27<=1500000,"Medium",IF(Q27<=10000000,"Large","Mega")))) -> (n/a) | S27: Watch | T27: Cycle 2 TBD (Cycle 1 closed 2025-06-18) | U27: Recurring | V27: Rolling during open window | W27: peer_review | X27: 2 | Y27: CZI EOSS | Z27: sciencegrants@chanzuckerberg.com | AA27: https://chanzuckerberg.com/rfa/ | AB27: https://chanzuckerberg.com/science/science-funding/ | AC27: HTML | AD27: Virtual-cell / foundation-model biology; nonprofit-eligible | AE27: High | AF27: New | AG27: Not started | AH27: Angela Oliveira Pisco (Dir. Data Science, CZI; ex-insitro manager) — WARM
A28: F024 | B28: CZI Science — Essential Open Source Software (EOSS) Cycle 6 | C28: Chan Zuckerberg Initiative | D28: Philanthropic | E28: OSS grant | F28: grant | G28: Yes | H28: US/Intl | I28: PASS | J28: 4 | K28: 4 | L28: 5 | M28: 4 | N28: =ROUND(K28/5*3+L28/5*2.5+J28/5*2+M28/5*2.5,1) -> 8.5 | O28: 100000 | P28: 400000 | Q28: 250000 | R28: =IF(Q28="","(n/a)",IF(Q28<=250000,"Small",IF(Q28<=1500000,"Medium",IF(Q28<=10000000,"Large","Mega")))) -> Small | S28: Open | T28: LOI 2026-10-18 | U28: Recurring | V28: LOI Oct→invited full→2027 awards | W28: peer_review | X28: 2 | Y28: CZI AI/GPU RFA | Z28: — | AA28: https://chanzuckerberg.com/rfa/essential-open-source-software-for-science/ | AB28: https://chanzuckerberg.com/science/programs-resources/open-science/grants/ | AC28: HTML | AD28: Cytoverse open tools (Apache 2.0) near-perfect fit | AE28: High | AF28: New | AG28: Not started | AH28: Angela Oliveira Pisco (CZI) — WARM
A29: F025 | B29: McKnight — Technology Awards (neuro tools) | C29: McKnight Endowment for Neuroscience | D29: Philanthropic | E29: Innovation grant | F29: grant | G29: Yes | H29: US | I29: PASS | J29: 3 | K29: 5 | L29: 4 | M29: 3 | N29: =ROUND(K29/5*3+L29/5*2.5+J29/5*2+M29/5*2.5,1) -> 7.7 | Q29: 200000 | R29: =IF(Q29="","(n/a)",IF(Q29<=250000,"Small",IF(Q29<=1500000,"Medium",IF(Q29<=10000000,"Large","Mega")))) -> Small | S29: Watch | T29: Opens ~Aug 1 2026 | U29: Recurring | V29: Annual; ~$200K/yr x2 | W29: peer_review | X29: 2 | Y29: BBRF; Allen ADI | Z29: — | AA29: https://www.mcknight.org/programs/the-mcknight-endowment-fund-for-neuroscience/technology-awards/ | AB29: https://www.mcknight.org | AC29: HTML | AD29: 'New & unusual approaches to brain function' = Cytoscope | AE29: High | AF29: New
A30: F026 | B30: Tiny Blue Dot Foundation — Perception Box (Round 5) | C30: Tiny Blue Dot Foundation | D30: Philanthropic | E30: Research grant | F30: grant | G30: Yes (501c3) | H30: Intl | I30: PASS | J30: 3 | K30: 5 | L30: 4 | M30: 4 | N30: =ROUND(K30/5*3+L30/5*2.5+J30/5*2+M30/5*2.5,1) -> 8.2 | P30: 900000 | Q30: 500000 | R30: =IF(Q30="","(n/a)",IF(Q30<=250000,"Small",IF(Q30<=1500000,"Medium",IF(Q30<=10000000,"Large","Mega")))) -> Medium | S30: Watch | T30: ~Sep LOI (annual) | U30: Recurring | V30: LOI Sep→Dec select→spring full; ≤$900K/3yr | W30: peer_review | X30: 2 | Y30: OneMind RSA | Z30: — | AA30: https://www.tinybluedotfoundation.org/research/rfp | AB30: https://www.tinybluedotfoundation.org/ | AC30: HTML | AD30: Brain constructs reality + AI/neuromod/wearables; 501c3 eligible | AE30: High | AF30: New
A31: F027 | B31: Simons Foundation — SFARI New Ideas Award | C31: Simons Foundation | D31: Philanthropic | E31: Research grant | F31: grant | G31: Yes (independent PI) | H31: US/Intl | I31: PASS | J31: 2 | K31: 4 | L31: 4 | M31: 3 | N31: =ROUND(K31/5*3+L31/5*2.5+J31/5*2+M31/5*2.5,1) -> 6.7 | O31: 100000 | P31: 300000 | Q31: 200000 | R31: =IF(Q31="","(n/a)",IF(Q31<=250000,"Small",IF(Q31<=1500000,"Medium",IF(Q31<=10000000,"Large","Mega")))) -> Small | S31: Rolling | T31: LOI rolling from 2026-04-29 | U31: Rolling | V31: LOI→3-4mo decision | W31: peer_review | X31: 2 | Y31: SCGB | Z31: — | AA31: https://www.sfari.org/grant/new-ideas-request-for-applications/ | AB31: https://www.sfari.org/funding-opportunities/ | AC31: HTML | AD31: Autism/NDD precision phenotyping adjacent to pilot | AE31: High | AF31: New
A32: F028 | B32: CIAPM — Precision Medicine Research (CA) | C32: CA Initiative to Advance Precision Medicine | D32: Government | E32: State grant | F32: grant | G32: Partial (CA-based) | H32: CA | I32: PASS | J32: 4 | K32: 5 | L32: 4 | M32: 3 | N32: =ROUND(K32/5*3+L32/5*2.5+J32/5*2+M32/5*2.5,1) -> 8.1 | O32: 1200000 | P32: 2000000 | Q32: 1500000 | R32: =IF(Q32="","(n/a)",IF(Q32<=250000,"Small",IF(Q32<=1500000,"Medium",IF(Q32<=10000000,"Large","Mega")))) -> Medium | S32: Watch | T32: Next cycle on CA budget (~summer) | U32: Recurring | V32: LOI→full→award; 2.5yr | W32: internal_panel | X32: 2 | Y32: UCSF AIM; Stanford PMHW | Z32: CHHS; CA partners | AA32: https://ciapm-chhs.submittable.com/submit | AB32: https://ciapm.chhs.ca.gov/activity/news.html | AC32: HTML | AD32: Depression precision medicine + equity; CA HQ is an asset | AE32: High | AF32: New
A33: F029 | B33: Fast Forward — Tech-Nonprofit Accelerator (2027) | C33: Fast Forward | D33: Philanthropic | E33: Accelerator + grant | F33: grant | G33: Yes (tech-nonprofit) | H33: Intl | I33: PASS | J33: 4 | K33: 3 | L33: 4 | M33: 5 | N33: =ROUND(K33/5*3+L33/5*2.5+J33/5*2+M33/5*2.5,1) -> 7.9 | O33: 25000 | Q33: 25000 | R33: =IF(Q33="","(n/a)",IF(Q33<=250000,"Small",IF(Q33<=1500000,"Medium",IF(Q33<=10000000,"Large","Mega")))) -> Small | S33: Watch | T33: Apps 2026-07-30 to 09-08 | U33: Recurring | V33: Apply Jul-Sep→Feb-May 2027 program; $25K+ unrestricted | W33: internal_panel | X33: 2 | Y33: Google.org GenAI | Z33: ffwd.org newsletters | AA33: https://www.ffwd.org/accelerator | AB33: https://www.ffwd.org/accelerator | AC33: Newsletter | AD33: Only accelerator built for AI/tech nonprofits; exact 501c3 fit | AE33: High | AF33: Refresh
A34: F030 | B34: Speculative Technologies — Brains Accelerator (2027) | C34: Speculative Technologies | D34: FRO / Moonshot | E34: Accelerator | F34: in-kind | G34: Yes (individual) | H34: US | I34: PASS | J34: 4 | K34: 3 | L34: 5 | M34: 5 | N34: =ROUND(K34/5*3+L34/5*2.5+J34/5*2+M34/5*2.5,1) -> 8.4 | R34: =IF(Q34="","(n/a)",IF(Q34<=250000,"Small",IF(Q34<=1500000,"Medium",IF(Q34<=10000000,"Large","Mega")))) -> (n/a) | S34: Watch | T34: Apps open ~Oct 2026 | U34: Recurring | V34: 15wk part-time; connects to FRO funders | W34: internal_panel | X34: 2 | Y34: Convergent FRO; Renaissance | Z34: Ben Reinhardt | AA34: https://spec.tech/brains | AB34: https://spec.tech/brains | AC34: Newsletter | AD34: Develop Cytoverse/Cytoscope as coordinated research program | AE34: High | AF34: Refresh | AG34: Applied — rejected | AH34: Reapply 2027 with reframe; Ben Reinhardt
A35: F031 | B35: Astera Institute — Residency (Spring 2027) | C35: Astera Institute | D35: FRO / Moonshot | E35: Residency | F35: fellowship | G35: Yes (individual) | H35: US (onsite Emeryville) | I35: PASS | J35: 5 | K35: 4 | L35: 5 | M35: 4 | N35: =ROUND(K35/5*3+L35/5*2.5+J35/5*2+M35/5*2.5,1) -> 8.9 | O35: 125000 | P35: 1500000 | Q35: 500000 | R35: =IF(Q35="","(n/a)",IF(Q35<=250000,"Small",IF(Q35<=1500000,"Medium",IF(Q35<=10000000,"Large","Mega")))) -> Medium | S35: Watch | T35: Next cycle ~fall 2026 (closed 04-19) | U35: Recurring | V35: Apply→admit; salary + ≤$1.5M project | W35: internal_panel | X35: 2 | Y35: Convergent FRO | Z35: Astera Substack | AA35: https://astera.org/residency/ | AB35: https://astera.org/residency/ | AC35: Newsletter | AD35: Neuro-AI + open science; pre-commercial; was prior denial | AE35: High | AF35: Refresh | AG35: Applied — rejected | AH35: Reapply Spring 2027; Neuro-AI/open-science framing
A36: F032 | B36: Activate — Cyclotron Road Fellowship (2027) | C36: Activate | D36: Philanthropic | E36: Fellowship | F36: fellowship | G36: Yes (individual, no equity) | H36: US | I36: PASS | J36: 2 | K36: 3 | L36: 4 | M36: 4 | N36: =ROUND(K36/5*3+L36/5*2.5+J36/5*2+M36/5*2.5,1) -> 6.6 | O36: 300000 | Q36: 300000 | R36: =IF(Q36="","(n/a)",IF(Q36<=250000,"Small",IF(Q36<=1500000,"Medium",IF(Q36<=10000000,"Large","Mega")))) -> Medium | S36: Watch | T36: Apps ~Oct 2026 | U36: Recurring | V36: >$300K/2yr stipend + R&D; no equity | W36: expert_committee | X36: 2 | Y36: NSF X-Labs | Z36: — | AA36: https://activate.org/apply | AB36: https://activate.org/the-fellowship | AC36: HTML | AD36: Hardware/sensor vertical for Cytoscope; founder-led | AE36: High | AF36: New
A37: F033 | B37: BBRF — NARSAD Young Investigator Grant | C37: Brain & Behavior Research Foundation | D37: Mental-Health Foundation | E37: Research grant | F37: grant | G37: Partial (institution host) | H37: US | I37: BACKUP | J37: 2 | K37: 5 | L37: 3 | M37: 3 | N37: =ROUND(K37/5*3+L37/5*2.5+J37/5*2+M37/5*2.5,1) -> 6.8 | O37: 70000 | P37: 70000 | Q37: 70000 | R37: =IF(Q37="","(n/a)",IF(Q37<=250000,"Small",IF(Q37<=1500000,"Medium",IF(Q37<=10000000,"Large","Mega")))) -> Small | S37: Watch | T37: Annual ~Feb | U37: Recurring | V37: Feb open→fall decision; $70K/2yr | W37: expert_committee | X37: 2 | Y37: NIMH R21 | Z37: — | AA37: https://bbrfoundation.org/grants-prizes/bbrf-young-investigator-grants | AB37: https://bbrfoundation.org/grants-prizes/grants | AC37: HTML | AD37: Dx tools/biomarkers for depression/anxiety/psychosis; needs faculty-equiv host | AE37: High | AF37: New
A38: F034 | B38: AFSP — Focus / Innovation Research Grants | C38: American Foundation for Suicide Prevention | D38: Mental-Health Foundation | E38: Research grant | F38: grant | G38: Yes (nonprofit) | H38: US | I38: PASS | J38: 2 | K38: 5 | L38: 3 | M38: 3 | N38: =ROUND(K38/5*3+L38/5*2.5+J38/5*2+M38/5*2.5,1) -> 6.8 | O38: 50000 | P38: 500000 | Q38: 125000 | R38: =IF(Q38="","(n/a)",IF(Q38<=250000,"Small",IF(Q38<=1500000,"Medium",IF(Q38<=10000000,"Large","Mega")))) -> Small | S38: Watch | T38: LOI ~Aug; full ~Nov-Dec | U38: Recurring | V38: LOI Aug→full Dec→May decision | W38: expert_committee | X38: 2 | Y38: NIMH | Z38: — | AA38: https://afsp.org/research-grant-information/ | AB38: https://afsp.org/research-grants/ | AC38: HTML | AD38: Suicide-risk biomarkers in-scope; nonprofit institution eligible | AE38: High | AF38: New
A39: F035 | B39: Coefficient Giving — Science & Global Health R&D | C39: Coefficient Giving (ex-Open Phil) | D39: Philanthropic | E39: Major grant | F39: grant | G39: Yes | H39: US/Intl | I39: PASS | J39: 2 | K39: 4 | L39: 4 | M39: 3 | N39: =ROUND(K39/5*3+L39/5*2.5+J39/5*2+M39/5*2.5,1) -> 6.7 | O39: 500000 | P39: 10000000 | Q39: 2000000 | R39: =IF(Q39="","(n/a)",IF(Q39<=250000,"Small",IF(Q39<=1500000,"Medium",IF(Q39<=10000000,"Large","Mega")))) -> Large | S39: Rolling | T39: Proactive / unsolicited (~1-2%) | U39: Rolling | V39: 1-2pg brief→PO response; 5-12mo | W39: program-officer | X39: 2 | Y39: EA Funds | Z39: science@coefficientgiving.org | AA39: https://coefficientgiving.org/apply-for-funding/ | AB39: https://coefficientgiving.org/funds/ | AC39: HTML | AD39: Big philanthropy; neglected-disease framing needed; cold path | AE39: High | AF39: Refresh | AG39: Planned | AH39: science@coefficientgiving.org (cold)
A40: F036 | B40: Google.org — Generative AI Accelerator | C40: Google.org | D40: Corporate | E40: Accelerator + grant | F40: grant | G40: Yes | H40: Intl/US | I40: PASS | J40: 5 | K40: 3 | L40: 4 | M40: 4 | N40: =ROUND(K40/5*3+L40/5*2.5+J40/5*2+M40/5*2.5,1) -> 7.8 | O40: 500000 | P40: 2000000 | Q40: 1000000 | R40: =IF(Q40="","(n/a)",IF(Q40<=250000,"Small",IF(Q40<=1500000,"Medium",IF(Q40<=10000000,"Large","Mega")))) -> Medium | S40: Watch | T40: ~fall 2026 (2025 cohort selected) | U40: Recurring | V40: Annual; 6-mo pro-bono + credits + ≥$500K | W40: program-officer | X40: 2 | Y40: Google.org AI for Science | Z40: — | AA40: https://impactchallenge.withgoogle.com/genaiaccelerator | AB40: https://blog.google/outreach-initiatives/google-org/ | AC40: HTML | AD40: GenAI for health; Cytonome on-device angle | AE40: Med | AF40: New
A41: F037 | B41: NSF Convergence Accelerator (next cohort) | C41: NSF (TIP) | D41: Government | E41: Cooperative agreement | F41: grant | G41: Yes | H41: US | I41: PASS | J41: 4 | K41: 3 | L41: 4 | M41: 4 | N41: =ROUND(K41/5*3+L41/5*2.5+J41/5*2+M41/5*2.5,1) -> 7.4 | O41: 750000 | P41: 5000000 | Q41: 2000000 | R41: =IF(Q41="","(n/a)",IF(Q41<=250000,"Small",IF(Q41<=1500000,"Medium",IF(Q41<=10000000,"Large","Mega")))) -> Large | S41: Watch | T41: Next DCL TBD | U41: Recurring | V41: Ideation→Ph1 ≤$750K→Ph2 ≤$5M | W41: peer_review | X41: 2 | Y41: NSF X-Labs | Z41: — | AA41: https://www.nsf.gov/funding/initiatives/convergence-accelerator | AB41: https://www.nsf.gov/funding/initiatives/convergence-accelerator | AC41: RSS(NSF) | AD41: Health+AI track if released; consortium model | AE41: Med | AF41: Existing
A42: F038 | B42: NSF–NIH Smart Health & Biomedical Research | C42: NSF / NIH | D42: Government | E42: Research grant | F42: grant | G42: Yes | H42: US | I42: PASS | J42: 4 | K42: 4 | L42: 4 | M42: 3 | N42: =ROUND(K42/5*3+L42/5*2.5+J42/5*2+M42/5*2.5,1) -> 7.5 | P42: 1200000 | Q42: 1200000 | R42: =IF(Q42="","(n/a)",IF(Q42<=250000,"Small",IF(Q42<=1500000,"Medium",IF(Q42<=10000000,"Large","Mega")))) -> Medium | S42: Watch | T42: Annual ~Sep-Oct | U42: Recurring | V42: ~$1.2M/4yr | W42: peer_review | X42: 2 | Y42: NIMH | Z42: — | AA42: https://www.nsf.gov/funding/opportunities/sch-smart-health-biomedical-research-era-artificial-intelligence/nsf25-542/solicitation | AB42: https://www.nsf.gov/funding/opportunities | AC42: RSS(NSF) | AD42: Multimodal AI sensing in health | AE42: Med | AF42: Existing
A43: F039 | B43: PCORI — Methods (AI/ML in patient-centered research) | C43: PCORI | D43: Government | E43: Methods grant | F43: grant | G43: Yes | H43: US | I43: PASS | J43: 4 | K43: 4 | L43: 3 | M43: 3 | N43: =ROUND(K43/5*3+L43/5*2.5+J43/5*2+M43/5*2.5,1) -> 7 | P43: 750000 | Q43: 750000 | R43: =IF(Q43="","(n/a)",IF(Q43<=250000,"Small",IF(Q43<=1500000,"Medium",IF(Q43<=10000000,"Large","Mega")))) -> Medium | S43: Watch | T43: LOI cycle (~Apr); next cycle | U43: Recurring | V43: LOI→full→~9mo | W43: peer_review | X43: 2 | Y43: NSF Smart Health | Z43: — | AA43: https://www.pcori.org/funding-opportunities | AB43: https://www.pcori.org/funding-opportunities | AC43: HTML | AD43: AI/ML methods for patient-centered research | AE43: High | AF43: Existing
A44: F040 | B44: UK ARIA — Scalable / Precision Neurotechnologies | C44: ARIA (UK) | D44: Government | E44: Programme | F44: grant | G44: Yes (intl path) | H44: UK/US-path | I44: PASS | J44: 4 | K44: 5 | L44: 5 | M44: 4 | N44: =ROUND(K44/5*3+L44/5*2.5+J44/5*2+M44/5*2.5,1) -> 9.1 | O44: 650000 | P44: 5000000 | Q44: 2000000 | R44: =IF(Q44="","(n/a)",IF(Q44<=250000,"Small",IF(Q44<=1500000,"Medium",IF(Q44<=10000000,"Large","Mega")))) -> Large | S44: Watch | T44: Next call (program-specific) | U44: Single | V44: Concept paper→full proposal | W44: program-officer | X44: 2 | Y44: UK partner | Z44: ARIA substack | AA44: https://www.aria.org.uk/opportunity-spaces/scalable-neural-interfaces/ | AB44: https://www.aria.org.uk/funding-opportunities/ | AC44: HTML | AD44: Noninvasive neural readout + circuit-level brain = Cytoscope | AE44: High | AF44: Refresh
A45: F041 | B45: UK ARIA — Opportunity Seeds (rolling) | C45: ARIA (UK) | D45: Government | E45: Seed grant | F45: grant | G45: Yes (intl path) | H45: UK/US-path | I45: PASS | J45: 3 | K45: 3 | L45: 5 | M45: 5 | N45: =ROUND(K45/5*3+L45/5*2.5+J45/5*2+M45/5*2.5,1) -> 8 | P45: 650000 | Q45: 400000 | R45: =IF(Q45="","(n/a)",IF(Q45<=250000,"Small",IF(Q45<=1500000,"Medium",IF(Q45<=10000000,"Large","Mega")))) -> Medium | S45: Watch | T45: Rolling per opportunity space | U45: Rolling | V45: Short seed proposal | W45: program-officer | X45: 2 | Y45: ARIA programmes | Z45: — | AA45: https://www.aria.org.uk/funding-opportunities/ | AB45: https://www.aria.org.uk/funding-opportunities/ | AC45: HTML | AD45: Fast small seeds to enter ARIA orbit | AE45: Med | AF45: Existing
A46: F042 | B46: Allen Distinguished Investigator (ADI) | C46: Allen Institute / Frontiers Group | D46: Philanthropic | E46: Investigator grant | F46: grant | G46: Yes (nonprofit-eligible) | H46: US/Intl | I46: BACKUP | J46: 3 | K46: 4 | L46: 5 | M46: 3 | N46: =ROUND(K46/5*3+L46/5*2.5+J46/5*2+M46/5*2.5,1) -> 7.6 | O46: 1000000 | P46: 1500000 | Q46: 1200000 | R46: =IF(Q46="","(n/a)",IF(Q46<=250000,"Small",IF(Q46<=1500000,"Medium",IF(Q46<=10000000,"Large","Mega")))) -> Medium | S46: Watch | T46: Call ~every 1-2yr (verify open) | U46: Recurring | V46: LOI→invited full | W46: expert_committee | X46: 2 | Y46: CZI; Simons | Z46: allenfrontiersgroup@alleninstitute.org | AA46: https://alleninstitute.org/division/frontiers-group/open-calls-science-funding/ | AB46: https://alleninstitute.org/news | AC46: HTML | AD46: 'Reinvent entire fields'; nonprofit-eligible; confirm cycle | AE46: Med | AF46: New | AG46: Not started | AH46: Hani Goodarzi (Arc; Virtual Cell + AD effort) — same-highschool tie
A47: F043 | B47: Renaissance Philanthropy — Big-if-True Science Accelerator | C47: Renaissance Philanthropy | D47: FRO / Moonshot | E47: Accelerator | F47: in-kind | G47: Yes | H47: US/Intl | I47: PASS | J47: 4 | K47: 3 | L47: 5 | M47: 5 | N47: =ROUND(K47/5*3+L47/5*2.5+J47/5*2+M47/5*2.5,1) -> 8.4 | R47: =IF(Q47="","(n/a)",IF(Q47<=250000,"Small",IF(Q47<=1500000,"Medium",IF(Q47<=10000000,"Large","Mega")))) -> (n/a) | S47: Rolling | T47: Contact for next cohort | U47: Rolling | V47: Application→program→funder placement | W47: internal_panel | X47: 2 | Y47: Convergent; Spec.tech | Z47: info@renphil.org | AA47: https://www.renaissancephilanthropy.org/programs | AB47: https://www.renaissancephilanthropy.org/programs | AC47: Newsletter | AD47: Coordinated-research-program design + ARPA placement | AE47: High | AF47: New
A48: F044 | B48: EA Infrastructure Fund | C48: Effective Altruism Funds | D48: EA / Longtermist | E48: Grant | F48: grant | G48: Yes | H48: Intl | I48: PASS | J48: 2 | K48: 2 | L48: 3 | M48: 5 | N48: =ROUND(K48/5*3+L48/5*2.5+J48/5*2+M48/5*2.5,1) -> 6 | O48: 50000 | P48: 500000 | Q48: 150000 | R48: =IF(Q48="","(n/a)",IF(Q48<=250000,"Small",IF(Q48<=1500000,"Medium",IF(Q48<=10000000,"Large","Mega")))) -> Small | S48: Rolling | T48: Rolling (monthly review) | U48: Rolling | V48: Apply→1-3mo→fast disbursement | W48: program-officer | X48: 2 | Y48: Manifund; SFF | Z48: — | AA48: https://funds.effectivealtruism.org/apply-for-funding | AB48: https://funds.effectivealtruism.org/grants | AC48: HTML | AD48: Fast unrestricted runway; mission-fit needs framing | AE48: Med | AF48: Existing
A49: F045 | B49: NIH Bridge2AI (Stage II) | C49: NIH Common Fund | D49: Government | E49: Program grant | F49: grant | G49: Yes | H49: US | I49: PASS | J49: 5 | K49: 4 | L49: 5 | M49: 3 | N49: =ROUND(K49/5*3+L49/5*2.5+J49/5*2+M49/5*2.5,1) -> 8.4 | R49: =IF(Q49="","(n/a)",IF(Q49<=250000,"Small",IF(Q49<=1500000,"Medium",IF(Q49<=10000000,"Large","Mega")))) -> (n/a) | S49: Watch | T49: ~2026-07-01 / next FOA | U49: Recurring | V49: Consortium scale; multi-yr | W49: peer_review | X49: 2 | Y49: PRIMED-AI | Z49: — | AA49: https://bridge2ai.org/ | AB49: https://commonfund.nih.gov/bridge2ai | AC49: RSS(NIH Guide) | AD49: AI-ready biomedical data ethos = Cytoverse | AE49: Med | AF49: Existing
A50: F046 | B50: NIH PRIMED-AI | C50: NIH Common Fund | D50: Government | E50: Program grant | F50: grant | G50: Yes | H50: US | I50: PASS | J50: 5 | K50: 4 | L50: 4 | M50: 3 | N50: =ROUND(K50/5*3+L50/5*2.5+J50/5*2+M50/5*2.5,1) -> 7.9 | Q50: 25000000 | R50: =IF(Q50="","(n/a)",IF(Q50<=250000,"Small",IF(Q50<=1500000,"Medium",IF(Q50<=10000000,"Large","Mega")))) -> Mega | S50: Watch | T50: Solicitations expected 2026 | U50: Recurring | V50: Listserv→FOA→full | W50: peer_review | X50: 2 | Y50: Bridge2AI | Z50: commonfund.nih.gov/primed-ai | AA50: https://commonfund.nih.gov/primed-ai | AB50: https://commonfund.nih.gov/primed-ai | AC50: RSS(NIH Guide) | AD50: Precision-medicine AI program; monitor for FOA | AE50: Med | AF50: Existing
A51: F047 | B51: Wellcome Leap — MCPsych / follow-on programs | C51: Wellcome Leap | D51: FRO / Moonshot | E51: Program | F51: grant | G51: Yes (via HBNet) | H51: Intl/US | I51: PASS | J51: 4 | K51: 5 | L51: 4 | M51: 4 | N51: =ROUND(K51/5*3+L51/5*2.5+J51/5*2+M51/5*2.5,1) -> 8.6 | O51: 500000 | P51: 5000000 | Q51: 2500000 | R51: =IF(Q51="","(n/a)",IF(Q51<=250000,"Small",IF(Q51<=1500000,"Medium",IF(Q51<=10000000,"Large","Mega")))) -> Large | S51: Watch | T51: Performer calls via HBNet | U51: Recurring | V51: Program-director model; fast cycles | W51: program-officer | X51: 3 | Y51: HBNet (F005) | Z51: Susanne Ahmari (MCPsych) | AA51: https://wellcomeleap.org/mcpsych/ | AB51: https://wellcomeleap.org/ | AC51: Newsletter | AD51: Anhedonic depression multimodal+AI = Cytoverse meso+MH | AE51: High | AF51: Refresh
A52: F048 | B52: Wellcome Trust — Mental Health Award: Stratification | C52: Wellcome Trust | D52: Philanthropic | E52: Research grant | F52: grant | G52: Yes (intl) | H52: Intl/US | I52: PASS | J52: 4 | K52: 5 | L52: 4 | M52: 3 | N52: =ROUND(K52/5*3+L52/5*2.5+J52/5*2+M52/5*2.5,1) -> 8.1 | O52: 1000000 | P52: 5000000 | Q52: 3000000 | R52: =IF(Q52="","(n/a)",IF(Q52<=250000,"Small",IF(Q52<=1500000,"Medium",IF(Q52<=10000000,"Large","Mega")))) -> Large | S52: Watch | T52: Verify current call status | U52: Single | V52: LOI/foundation→full; multi-phase | W52: peer_review | X52: 3 | Y52: Wellcome Leap MCPsych | Z52: — | AA52: https://wellcome.org/research-funding/schemes/mental-health-award-finding-right-treatment-right-people-right-time | AB52: https://wellcome.org/research-funding/guidance/prepare-to-apply/scheme-application-deadlines | AC52: HTML | AD52: Biotyping/stratification of depression/anxiety = exact pilot; VERIFY | AE52: Med | AF52: New | AG52: Not started — verify call status | AH52: Wellcome MH team
A53: F049 | B53: ARPA-H — SBIR/STTR | C53: ARPA-H | D53: Government | E53: SBIR/STTR | F53: grant | G53: Path-via-PBC | H53: US | I53: BACKUP | J53: 3 | K53: 4 | L53: 3 | M53: 2 | N53: =ROUND(K53/5*3+L53/5*2.5+J53/5*2+M53/5*2.5,1) -> 6.1 | O53: 600000 | P53: 3500000 | Q53: 2000000 | R53: =IF(Q53="","(n/a)",IF(Q53<=250000,"Small",IF(Q53<=1500000,"Medium",IF(Q53<=10000000,"Large","Mega")))) -> Large | S53: Watch | T53: SS target ~2026-07-10 | U53: Recurring | V53: Phase I ≤$600K→Phase II ≤$3.5M | W53: program-officer | X53: 3 | Y53: ARPA-H ISOs | Z53: Proposers' Day Jun 11 | AA53: https://arpa-h.gov/explore-funding/sbir | AB53: https://arpa-h.gov/explore-funding/sbir | AC53: API(SAM.gov) | AD53: Strong fit but for-profit only; PBC path | AE53: High | AF53: New
A54: F050 | B54: NIMH — SBIR/STTR (digital MH / neurotech) | C54: NIH / NIMH | D54: Government | E54: SBIR/STTR | F54: grant | G54: Path-via-PBC | H54: US | I54: BACKUP | J54: 4 | K54: 5 | L54: 4 | M54: 2 | N54: =ROUND(K54/5*3+L54/5*2.5+J54/5*2+M54/5*2.5,1) -> 7.6 | O54: 300000 | P54: 2000000 | Q54: 1000000 | R54: =IF(Q54="","(n/a)",IF(Q54<=250000,"Small",IF(Q54<=1500000,"Medium",IF(Q54<=10000000,"Large","Mega")))) -> Medium | S54: Watch | T54: Omnibus deadlines (3/yr) | U54: Recurring | V54: Phase I ≤$300K→Phase II ≤$2M; STTR allows nonprofit partner | W54: peer_review | X54: 3 | Y54: NIMH R21 | Z54: — | AA54: https://www.nimh.nih.gov/funding/sbir | AB54: https://www.nimh.nih.gov/funding/sbir | AC54: RSS(NIH Guide) | AD54: Excellent post-PBC; STTR lets nonprofit partner | AE54: High | AF54: New
A55: F051 | B55: OneMind — Accelerator (digital MH) | C55: One Mind | D55: Mental-Health Foundation | E55: Accelerator | F55: equity | G55: Path-via-PBC | H55: US | I55: BACKUP | J55: 4 | K55: 5 | L55: 4 | M55: 2 | N55: =ROUND(K55/5*3+L55/5*2.5+J55/5*2+M55/5*2.5,1) -> 7.6 | R55: =IF(Q55="","(n/a)",IF(Q55<=250000,"Small",IF(Q55<=1500000,"Medium",IF(Q55<=10000000,"Large","Mega")))) -> (n/a) | S55: Watch | T55: Apps ~Sep (2027 cohort) | U55: Recurring | V55: 10wk; advisory equity; investor/payer network | W55: internal_panel | X55: 3 | Y55: OneMind RSA/OMLEC | Z55: Carmine Di Maro (ED) | AA55: https://onemind.org/what-we-do/one-mind-accelerator/ | AB55: https://onemind.org/what-we-do/one-mind-accelerator/ | AC55: HTML | AD55: Portfolio already funds brain-wearable + MH foundation models; PBC path | AE55: High | AF55: New
A56: F052 | B56: Techstars AI Health (Baltimore) | C56: Techstars | D56: Venture Capital | E56: Accelerator + investment | F56: investment | G56: No (PBC) | H56: US | I56: BACKUP | J56: 5 | K56: 5 | L56: 2 | M56: 2 | N56: =ROUND(K56/5*3+L56/5*2.5+J56/5*2+M56/5*2.5,1) -> 7 | O56: 220000 | P56: 220000 | Q56: 220000 | R56: =IF(Q56="","(n/a)",IF(Q56<=250000,"Small",IF(Q56<=1500000,"Medium",IF(Q56<=10000000,"Large","Mega")))) -> Small | S56: Open | T56: 2026-06-10 (Fall cohort) | U56: Recurring | V56: $220K SAFE; ~6-9% equity; Sep-Dec program | W56: due_diligence | X56: 3 | Y56: Northwestern Medicine TS | Z56: Johns Hopkins ecosystem | AA56: https://www.techstars.com/accelerators/baltimore-ai-health | AB56: https://www.techstars.com/accelerators | AC56: HTML | AD56: AI health; PBC-only (equity); strong once for-profit arm exists | AE56: High | AF56: New
A57: F053 | B57: EU Horizon Europe — Cluster 1 Health | C57: European Commission | D57: Intergovernmental | E57: Consortium grant | F57: grant | G57: Partner (US self-funded Associated Partner; anchor via UK/EU) | H57: EU (US 3rd-country) | I57: BACKUP | J57: 3 | K57: 4 | L57: 5 | M57: 3 | N57: =ROUND(K57/5*3+L57/5*2.5+J57/5*2+M57/5*2.5,1) -> 7.6 | O57: 1000000 | P57: 8000000 | Q57: 6000000 | R57: =IF(Q57="","(n/a)",IF(Q57<=250000,"Small",IF(Q57<=1500000,"Medium",IF(Q57<=10000000,"Large","Mega")))) -> Large | S57: Watch | T57: 2026-01 closed Apr 16; next single-stage ~Sep 15 2026; 2027 calls ~Apr 13 2027 | U57: Recurring | V57: Consortium-building 3-6mo lead; ≥3 entities/3 countries; UK (Manchester) can be funded coordinator | W57: peer_review | X57: 3 | Y57: EP PerMed; UKRI | Z57: Manchester/Madhvi (UK Horizon-funded since 2024); colleague w/ Horizon experience | AA57: https://research-and-innovation.ec.europa.eu/funding/funding-opportunities/funding-programmes-and-open-calls/horizon-europe/cluster-1-health_en | AB57: https://ec.europa.eu/info/funding-tenders/opportunities/portal | AC57: API(SEDIA CSV) | AD57: Highly value-aligned (open science + patient involvement mandates); €6-8M/project; US = self-funded partner, anchor via Manchester | AE57: Med | AF57: Refresh | AG57: Originally planned for expansion phase — start consortium-building NOW for Sep-2026 / 2027 calls | AH57: Manchester/Madhvi (UK = Horizon-funded since 2024); a colleague has Horizon experience
A58: F054 | B58: Gates Foundation — Grand Challenges (diagnostics) | C58: Gates Foundation | D58: Philanthropic | E58: Challenge grant | F58: grant | G58: Yes | H58: Intl (LMIC) | I58: PASS | J58: 3 | K58: 4 | L58: 4 | M58: 4 | N58: =ROUND(K58/5*3+L58/5*2.5+J58/5*2+M58/5*2.5,1) -> 7.6 | O58: 100000 | P58: 2000000 | Q58: 1000000 | R58: =IF(Q58="","(n/a)",IF(Q58<=250000,"Small",IF(Q58<=1500000,"Medium",IF(Q58<=10000000,"Large","Mega")))) -> Medium | S58: Closed-next | T58: ~annual (closed 04-28) | U58: Recurring | V58: Phase I ~$100K→Phase II ~$1M+ | W58: expert_committee | X58: 3 | Y58: — | Z58: gcgh.grandchallenges.org | AA58: https://gcgh.grandchallenges.org/ | AB58: https://gcgh.grandchallenges.org/challenges | AC58: HTML | AD58: Low-cost brain diagnostic for LMIC; watch 2026-27 cycle | AE58: High | AF58: Refresh
A59: F055 | B59: Schmidt Sciences — AI2050 / AI-for-Science | C59: Schmidt Sciences | D59: Philanthropic | E59: Fellowship / grant | F59: grant | G59: Partial (nomination) | H59: Intl/US | I59: BACKUP | J59: 5 | K59: 3 | L59: 4 | M59: 2 | N59: =ROUND(K59/5*3+L59/5*2.5+J59/5*2+M59/5*2.5,1) -> 6.8 | O59: 400000 | P59: 2500000 | Q59: 500000 | R59: =IF(Q59="","(n/a)",IF(Q59<=250000,"Small",IF(Q59<=1500000,"Medium",IF(Q59<=10000000,"Large","Mega")))) -> Medium | S59: Watch | T59: Closed-nomination; invitation | U59: Recurring | V59: Nomination→invited application | W59: invitation_only | X59: 3 | Y59: Convergent (funder) | Z59: — | AA59: https://www.schmidtsciences.org/opportunities | AB59: https://www.schmidtsciences.org/opportunities | AC59: HTML | AD59: AI×science broadly; no clear path without institutional nomination | AE59: Med | AF59: Existing
A60: F056 | B60: John Templeton Foundation — Life Sciences | C60: John Templeton Foundation | D60: Philanthropic | E60: Research grant | F60: grant | G60: Yes | H60: US/Intl | I60: PASS | J60: 2 | K60: 3 | L60: 3 | M60: 3 | N60: =ROUND(K60/5*3+L60/5*2.5+J60/5*2+M60/5*2.5,1) -> 5.6 | O60: 50000 | P60: 5000000 | Q60: 500000 | R60: =IF(Q60="","(n/a)",IF(Q60<=250000,"Small",IF(Q60<=1500000,"Medium",IF(Q60<=10000000,"Large","Mega")))) -> Medium | S60: Open | T60: OFI 2026-08-14; FP 2027-01-15 | U60: Recurring | V60: OFI Aug→Oct decision→FP Jan→2027 award | W60: program-officer | X60: 3 | Y60: Templeton World Charity | Z60: — | AA60: https://www.templeton.org | AB60: https://www.templeton.org | AC60: HTML | AD60: Life-sciences/flourishing; weaker without philosophy angle | AE60: High | AF60: New
A61: F057 | B61: Templeton World Charity — Accelerating Research on Consciousness | C61: Templeton World Charity Foundation | D61: Philanthropic | E61: Research grant | F61: grant | G61: Yes | H61: US/Intl | I61: BACKUP | J61: 3 | K61: 4 | L61: 4 | M61: 3 | N61: =ROUND(K61/5*3+L61/5*2.5+J61/5*2+M61/5*2.5,1) -> 7.1 | O61: 500000 | P61: 5000000 | Q61: 2000000 | R61: =IF(Q61="","(n/a)",IF(Q61<=250000,"Small",IF(Q61<=1500000,"Medium",IF(Q61<=10000000,"Large","Mega")))) -> Large | S61: Watch | T61: Periodic RFPs (adversarial collab.) | U61: Recurring | V61: Invitation via structured collaboration | W61: invitation_only | X61: 3 | Y61: JTF Life Sciences | Z61: info@templetonworldcharity.org | AA61: https://www.templetonworldcharity.org/our-priorities/discovery/accelerating-research-consciousness | AB61: https://www.templetonworldcharity.org | AC61: HTML | AD61: Cytoscope+Cytoverse for consciousness; AI×neuro sweet spot | AE61: Med | AF61: New
A62: F058 | B62: Arc Institute — Investigator / Ignite | C62: Arc Institute | D62: Philanthropic | E62: Institute appointment | F62: in-kind | G62: No (relocate/affiliate) | H62: US (Bay Area) | I62: BACKUP | J62: 4 | K62: 4 | L62: 5 | M62: 1 | N62: =ROUND(K62/5*3+L62/5*2.5+J62/5*2+M62/5*2.5,1) -> 7 | O62: 100000 | P62: 1000000 | R62: =IF(Q62="","(n/a)",IF(Q62<=250000,"Small",IF(Q62<=1500000,"Medium",IF(Q62<=10000000,"Large","Mega")))) -> (n/a) | S62: Invitation-only | T62: Recruited / partner-university only | U62: Recurring | V62: Internal hire / partner-univ faculty | W62: invitation_only | X62: Backup | Y62: — | Z62: Stanford/UCSF/UCB affiliation | AA62: https://arcinstitute.org/programs | AB62: https://arcinstitute.org/news | AC62: HTML | AD62: Top science fit but no external grant path; pursue as RESEARCH PARTNER | AE62: High | AF62: New | AG62: Not started | AH62: Hani Goodarzi (Arc; AD Initiative seeking external collaborators) — same-highschool; pursue as research partner
A63: F059 | B63: CZ Biohub SF — Investigator Program | C63: Chan Zuckerberg Biohub | D63: Philanthropic | E63: Investigator grant | F63: grant | G63: No (Stanford/UCSF/UCB only) | H63: US (Bay Area) | I63: BACKUP | J63: 4 | K63: 4 | L63: 5 | M63: 2 | N63: =ROUND(K63/5*3+L63/5*2.5+J63/5*2+M63/5*2.5,1) -> 7.5 | O63: 1000000 | P63: 1000000 | Q63: 1000000 | R63: =IF(Q63="","(n/a)",IF(Q63<=250000,"Small",IF(Q63<=1500000,"Medium",IF(Q63<=10000000,"Large","Mega")))) -> Medium | S63: Watch | T63: 3rd cohort ~2026-27 (univ-nominated) | U63: Recurring | V63: University-nominated | W63: invitation_only | X63: Backup | Y63: CZI EOSS | Z63: Bay Area faculty | AA63: https://czbiohub.org/sf/investigator-program/ | AB63: https://czbiohub.org | AC63: HTML | AD63: Affiliation-only; pursue via partner faculty | AE63: High | AF63: New
A64: F060 | B64: Simons — SCGB / Neuroscience Collaborations | C64: Simons Foundation | D64: Philanthropic | E64: Collaboration grant | F64: grant | G64: Partial (multi-PI; postdoc tracks) | H64: US/Intl | I64: BACKUP | J64: 3 | K64: 4 | L64: 4 | M64: 2 | N64: =ROUND(K64/5*3+L64/5*2.5+J64/5*2+M64/5*2.5,1) -> 6.6 | O64: 2000000 | P64: 50000000 | R64: =IF(Q64="","(n/a)",IF(Q64<=250000,"Small",IF(Q64<=1500000,"Medium",IF(Q64<=10000000,"Large","Mega")))) -> (n/a) | S64: Watch | T64: Vision-statement calls periodic | U64: Recurring | V64: Vision statement→invited full | W64: expert_committee | X64: Backup | Y64: SFARI New Ideas | Z64: — | AA64: https://www.simonsfoundation.org/funding-opportunities/ | AB64: https://www.simonsfoundation.org/funding-opportunities/ | AC64: HTML | AD64: Computational neuroscience fit; needs established multi-PI team | AE64: Med | AF64: New
A65: F061 | B65: Stanley Center for Psychiatric Research (Broad) | C65: Broad Institute | D65: Mental-Health Foundation | E65: Research partnership | F65: in-kind | G65: Partner-only | H65: US | I65: BACKUP | J65: 2 | K65: 5 | L65: 4 | M65: 2 | N65: =ROUND(K65/5*3+L65/5*2.5+J65/5*2+M65/5*2.5,1) -> 6.8 | R65: =IF(Q65="","(n/a)",IF(Q65<=250000,"Small",IF(Q65<=1500000,"Medium",IF(Q65<=10000000,"Large","Mega")))) -> (n/a) | S65: Invitation-only | T65: Relationship-based | U65: Rolling | V65: Collaboration via Broad investigator | W65: invitation_only | X65: Backup | Y65: Columbia SNF | Z65: Harvard/MIT network | AA65: https://www.broadinstitute.org/stanley-center-for-psychiatric-research | AB65: https://www.broadinstitute.org/stanley-center-for-psychiatric-research | AC65: HTML | AD65: World-class psychiatric genomics data; partner not funder | AE65: High | AF65: New
A66: F062 | B66: Humanity AI (pooled fund, 10 foundations) | C66: Humanity AI / RPA | D66: Philanthropic | E66: Initiative grant | F66: grant | G66: Yes | H66: US | I66: BACKUP | J66: 5 | K66: 1 | L66: 4 | M66: 4 | N66: =ROUND(K66/5*3+L66/5*2.5+J66/5*2+M66/5*2.5,1) -> 6.6 | O66: 100000 | P66: 500000 | Q66: 300000 | R66: =IF(Q66="","(n/a)",IF(Q66<=250000,"Small",IF(Q66<=1500000,"Medium",IF(Q66<=10000000,"Large","Mega")))) -> Medium | S66: Watch | T66: Open call ~summer 2026 | U66: Single | V66: Open call TBD | W66: internal_panel | X66: Backup | Y66: — | Z66: Doris Duke, MacArthur, Mozilla, etc. | AA66: https://humanityai.ai | AB66: https://humanityai.ai/news-and-updates/ | AC66: Newsletter | AD66: Focus = democracy/labor/education, NOT health/science; low fit | AE66: High | AF66: New
A67: F063 | B67: Lux Capital / Foresite Labs / Deep Science Ventures | C67: (various) | D67: Venture Capital | E67: Equity investment | F67: investment | G67: No (PBC) | H67: US/Intl | I67: BACKUP | J67: 4 | K67: 4 | L67: 2 | M67: 2 | N67: =ROUND(K67/5*3+L67/5*2.5+J67/5*2+M67/5*2.5,1) -> 6 | O67: 1000000 | P67: 10000000 | Q67: 5000000 | R67: =IF(Q67="","(n/a)",IF(Q67<=250000,"Small",IF(Q67<=1500000,"Medium",IF(Q67<=10000000,"Large","Mega")))) -> Large | S67: Rolling | T67: Rolling (warm intro) | U67: Rolling | V67: Pitch→diligence | W67: due_diligence | X67: Backup | Y67: PBC raise (Gate 1) | Z67: — | AA67: https://www.luxcapital.com/ | AB67: https://www.luxcapital.com/ | AC67: HTML | AD67: Mission-aligned deep-tech VC for the post-bifurcation PBC raise | AE67: Med | AF67: Existing | AG67: Applied — instant auto-reject (likely nonprofit / form-parameter mismatch) | AH67: Met program lead at SF Tech Week '24 — re-approach for manual review; OR pivot to NVIDIA Academic Grant (F016, nonprofit-eligible)
A68: F064 | B68: Wellcome Trust — Discovery Awards | C68: Wellcome Trust | D68: Philanthropic | E68: Research grant | F68: grant | G68: Yes (intl; institution) | H68: Intl/US | I68: BACKUP | J68: 3 | K68: 4 | L68: 4 | M68: 2 | N68: =ROUND(K68/5*3+L68/5*2.5+J68/5*2+M68/5*2.5,1) -> 6.6 | R68: =IF(Q68="","(n/a)",IF(Q68<=250000,"Small",IF(Q68<=1500000,"Medium",IF(Q68<=10000000,"Large","Mega")))) -> (n/a) | S68: Watch | T68: Annual rounds | U68: Recurring | V68: Multi-phase; team/institution | W68: peer_review | X68: Backup | Y68: Wellcome MH Award | Z68: — | AA68: https://wellcome.org/research-funding/schemes/wellcome-discovery-awards | AB68: https://wellcome.org/research-funding | AC68: HTML | AD68: Large discovery science; needs institutional track record | AE68: Med | AF68: Existing
A69: F065 | B69: Wellcome Trust — Prize for Mental Health Science | C69: Wellcome Trust | D69: Philanthropic | E69: Prize | F69: grant | G69: Yes | H69: Intl/US | I69: BACKUP | J69: 2 | K69: 5 | L69: 4 | M69: 2 | N69: =ROUND(K69/5*3+L69/5*2.5+J69/5*2+M69/5*2.5,1) -> 6.8 | O69: 250000 | P69: 1000000 | Q69: 1000000 | R69: =IF(Q69="","(n/a)",IF(Q69<=250000,"Small",IF(Q69<=1500000,"Medium",IF(Q69<=10000000,"Large","Mega")))) -> Medium | S69: Open | T69: 2026-09-18 (needs clinical evidence) | U69: Recurring | V69: Submit→panel | W69: expert_committee | X69: Backup | Y69: Wellcome MH Award | Z69: — | AA69: https://www.nature.com/immersive/wellcomeprizementalhealth/index.html | AB69: https://wellcome.org | AC69: HTML | AD69: Requires demonstrated outcome evidence; revisit after pilot data | AE69: High | AF69: New
A70: F066 | B70: Eli Lilly — Lilly Research Award Program (LRAP) | C70: Eli Lilly | D70: Corporate | E70: Research award | F70: grant | G70: Yes (needs Lilly scientist co-sponsor) | H70: US/Global | I70: PASS | J70: 5 | K70: 4 | L70: 4 | M70: 3 | N70: =ROUND(K70/5*3+L70/5*2.5+J70/5*2+M70/5*2.5,1) -> 7.9 | O70: 50000 | P70: 500000 | Q70: 250000 | R70: =IF(Q70="","(n/a)",IF(Q70<=250000,"Small",IF(Q70<=1500000,"Medium",IF(Q70<=10000000,"Large","Mega")))) -> Small | S70: Rolling | T70: Lilly-scientist co-initiated | U70: Rolling | V70: Find Lilly co-PI→joint proposal→review | W70: program-officer | X70: 1 | Y70: Lilly LPRC; Catalyze360 | Z70: Ananth Grama → Lilly (Purdue alliance) | AA70: https://www.lilly.com/science/partners/research-award-program | AB70: https://www.lilly.com/science/partners/research-award-program | AC70: Manual | AD70: Neurodegen+neuroscience tracks; warmest high-fit path via Ananth | AE70: Med | AF70: New | AG70: Not started | AH70: Ananth Grama (Board co-chair) → Lilly scientist co-sponsor
A71: F067 | B71: Eli Lilly–Purdue Research Alliance (LPRC) subaward | C71: Eli Lilly / Purdue IPAI | D71: Corporate | E71: Academic-industry partnership | F71: grant | G71: Path-via-partner (Purdue) | H71: US | I71: PASS | J71: 5 | K71: 3 | L71: 4 | M71: 4 | N71: =ROUND(K71/5*3+L71/5*2.5+J71/5*2+M71/5*2.5,1) -> 7.8 | O71: 50000 | P71: 500000 | Q71: 250000 | R71: =IF(Q71="","(n/a)",IF(Q71<=250000,"Small",IF(Q71<=1500000,"Medium",IF(Q71<=10000000,"Large","Mega")))) -> Small | S71: Rolling | T71: New projects through 2026 | U71: Rolling | V71: Via Purdue/IPAI→Lilly co-PI | W71: internal_panel | X71: 1 | Y71: Lilly LRAP | Z71: Ananth Grama (Board co-chair; directs IPAI; $250M Lilly–Purdue alliance) | AA71: https://lprc.purdue.edu | AB71: https://lprc.purdue.edu | AC71: Manual | AD71: 'Agentic drug discovery / AI for medicine' pillars = Cytoverse; most structurally available warm path | AE71: High | AF71: New | AG71: Not started | AH71: Ananth Grama directs Purdue IPAI ($250M Lilly–Purdue alliance) — WARM
A72: F068 | B72: Eli Lilly — Catalyze360 (Gateway Labs / TuneLab / ExploR&D / Ventures) | C72: Eli Lilly | D72: Corporate | E72: Incubator / venture | F72: hybrid | G72: Path-via-PBC | H72: US/Global | I72: BACKUP | J72: 5 | K72: 3 | L72: 3 | M72: 2 | N72: =ROUND(K72/5*3+L72/5*2.5+J72/5*2+M72/5*2.5,1) -> 6.3 | R72: =IF(Q72="","(n/a)",IF(Q72<=250000,"Small",IF(Q72<=1500000,"Medium",IF(Q72<=10000000,"Large","Mega")))) -> (n/a) | S72: Rolling | T72: Relationship-driven (invite) | U72: Rolling | V72: Reach out via connect-with-us | W72: invitation_only | X72: 3 | Y72: Lilly LRAP/LPRC | Z72: Ananth Grama → Catalyze360 leadership | AA72: https://www.lilly.com/science/partners/catalyze-360 | AB72: https://gatewaylabs.lilly.com | AC72: Manual | AD72: Lab/venture vehicles for the PBC phase; TuneLab federated AI adjacent to Cytoverse | AE72: Med | AF72: New | AG72: Not started | AH72: Ananth Grama → Catalyze360 leadership
A73: F069 | B73: Eli Lilly — Lilly Grant Office (education/QI) | C73: Eli Lilly | D73: Corporate | E73: Corporate grant | F73: grant | G73: Yes (nonprofit/health orgs) | H73: US/Intl | I73: PASS | J73: 1 | K73: 4 | L73: 3 | M73: 3 | N73: =ROUND(K73/5*3+L73/5*2.5+J73/5*2+M73/5*2.5,1) -> 5.8 | O73: 5000 | P73: 500000 | Q73: 100000 | R73: =IF(Q73="","(n/a)",IF(Q73<=250000,"Small",IF(Q73<=1500000,"Medium",IF(Q73<=10000000,"Large","Mega")))) -> Small | S73: Rolling | T73: EPFA-driven; apply anytime | U73: Rolling | V73: Online portal→8-16wk | W73: internal_panel | X73: 2 | Y73: — | Z73: — | AA73: https://grantoffice.lilly.com/grant-application | AB73: https://grantoffice.lilly.com/areas-of-focus | AC73: Manual | AD73: Neuroscience education/QI program, not R&D | AE73: Med | AF73: New | AG73: Not started | AH73: —
A74: F070 | B74: Nucleate × Eli Lilly — $100K Grand Challenge | C74: Nucleate / Eli Lilly | D74: Corporate | E74: Competition / non-dilutive grant | F74: grant | G74: Yes | H74: Global | I74: PASS | J74: 4 | K74: 5 | L74: 4 | M74: 4 | N74: =ROUND(K74/5*3+L74/5*2.5+J74/5*2+M74/5*2.5,1) -> 8.6 | O74: 100000 | P74: 100000 | Q74: 100000 | R74: =IF(Q74="","(n/a)",IF(Q74<=250000,"Small",IF(Q74<=1500000,"Medium",IF(Q74<=10000000,"Large","Mega")))) -> Small | S74: Closed-next | T74: 2026 closed 05-15; next ~Apr 2027 (ask re late entry as alumnus) | U74: Recurring | V74: Submit→finalists Jul→pitch Sep (Indianapolis) | W74: expert_committee | X74: 2 | Y74: Lilly LRAP; Nucleate Activator | Z74: PI is Nucleate alumnus (warm); Ananth → Catalyze360 | AA74: https://airtable.com/appT4HiIoA8FSzNnZ/pagx8AWPgWbg141a5/form | AB74: https://nucleatehq.medium.com/lilly-grand-challenge-2026-9e7de57735e3 | AC74: Newsletter | AD74: 'Cognitive & Sensory Health' track = Cytoscope/Cytonome; $100K non-dilutive + Lilly access | AE74: High | AF74: New | AG74: Missed 2026 (closed 05-15); ask re late entry | AH74: PI is Nucleate alumnus — WARM; Ananth → Lilly
A75: F071 | B75: Nucleate — Activator + alumni network | C75: Nucleate | D75: FRO / Moonshot | E75: Accelerator (no equity) | F75: in-kind | G75: Yes | H75: US/Intl (SF Bay) | I75: PASS | J75: 3 | K75: 4 | L75: 4 | M75: 5 | N75: =ROUND(K75/5*3+L75/5*2.5+J75/5*2+M75/5*2.5,1) -> 8.1 | R75: =IF(Q75="","(n/a)",IF(Q75<=250000,"Small",IF(Q75<=1500000,"Medium",IF(Q75<=10000000,"Large","Mega")))) -> (n/a) | S75: Watch | T75: 2027 cohort ~Oct 2026 apps | U75: Recurring | V75: Free; mentorship + VC/partner network | W75: internal_panel | X75: 2 | Y75: Nucleate×Lilly | Z75: PI is an alumnus; Bay Area branch has reached out repeatedly — WARM, unfollowed | AA75: https://nucleate.org/activator/ | AB75: https://nucleate.org/activator/ | AC75: Newsletter | AD75: Warm alumni tie; bio-entrepreneur network; hosts the Lilly Grand Challenge | AE75: High | AF75: New | AG75: Alumnus — WARM (Bay Area branch reached out repeatedly; unfollowed) | AH75: Reconnect with Nucleate Bay Area
A76: F072 | B76: Mayo Clinic Platform — Accelerate (digital health) | C76: Mayo Clinic | D76: Corporate | E76: Accelerator (equity) | F76: investment | G76: Path-via-PBC | H76: US/Intl | I76: BACKUP | J76: 5 | K76: 4 | L76: 3 | M76: 2 | N76: =ROUND(K76/5*3+L76/5*2.5+J76/5*2+M76/5*2.5,1) -> 6.9 | R76: =IF(Q76="","(n/a)",IF(Q76<=250000,"Small",IF(Q76<=1500000,"Medium",IF(Q76<=10000000,"Large","Mega")))) -> (n/a) | S76: Rolling | T76: Cohorts ~Feb/Oct; apply rolling | U76: Rolling | V76: Apply→interview→30wk; Mayo takes equity | W76: internal_panel | X76: 3 | Y76: Mayo Orchestrate | Z76: Ananth Grama Mayo ties (verify); Lilly–Mayo collab | AA76: https://surveys.mayoclinic.org/jfe/form/SV_8e8cPm3bhdq5XrE | AB76: https://www.mayoclinicplatform.org/focus-areas/digital-health/accelerate/ | AC76: Manual | AD76: AI-first + 40M-record clinical data for model validation; prior MH cohort cos; PBC path | AE76: High | AF76: New | AG76: Not started | AH76: Ananth Grama Mayo ties (verify); Lilly–Mayo collab
A77: F073 | B77: Mayo Clinic Platform — Orchestrate (data partnership) | C77: Mayo Clinic | D77: Corporate | E77: Data/research partnership | F77: hybrid | G77: Partner | H77: US/Intl | I77: BACKUP | J77: 5 | K77: 4 | L77: 3 | M77: 3 | N77: =ROUND(K77/5*3+L77/5*2.5+J77/5*2+M77/5*2.5,1) -> 7.4 | O77: 500000 | P77: 5000000 | Q77: 1000000 | R77: =IF(Q77="","(n/a)",IF(Q77<=250000,"Small",IF(Q77<=1500000,"Medium",IF(Q77<=10000000,"Large","Mega")))) -> Medium | S77: Rolling | T77: Customized engagement | U77: Rolling | V77: Contact→scope→contract | W77: internal_panel | X77: 3 | Y77: Mayo Accelerate | Z77: — | AA77: https://www.mayoclinicplatform.org/contact/ | AB77: https://www.mayoclinicplatform.org/focus-areas/biopharma/orchestrate/ | AC77: Manual | AD77: Longitudinal EHR + multiomics (40M) for Cytoverse training | AE77: Med | AF77: New | AG77: Not started | AH77: Ananth Grama Mayo ties (verify)
A78: F074 | B78: BRAIN Foundation — Research Grants (autism/NDD) | C78: BRAIN Foundation | D78: Mental-Health Foundation | E78: Research grant | F78: grant | G78: No-direct (needs PI host) / Partner | H78: US (SF Bay — Pleasanton) | I78: BACKUP | J78: 2 | K78: 5 | L78: 4 | M78: 3 | N78: =ROUND(K78/5*3+L78/5*2.5+J78/5*2+M78/5*2.5,1) -> 7.3 | O78: 90000 | P78: 180000 | Q78: 180000 | R78: =IF(Q78="","(n/a)",IF(Q78<=250000,"Small",IF(Q78<=1500000,"Medium",IF(Q78<=10000000,"Large","Mega")))) -> Small | S78: Watch | T78: Invite-only now; open RFP ~2027 | U78: Recurring | V78: 2yr; no overhead; needs institutional PI | W78: expert_committee | X78: 2 | Y78: Autism Society; SPARK | Z78: Sarika Agrawal (Co-founder & Board) — friend of Ananth; Pres. Pramila Srinivasan (Purdue PhD) | AA78: https://brainfoundation.org/how-to-apply/ | AB78: https://brainfoundation.org/how-to-apply/ | AC78: Newsletter | AD78: Autism biomarkers/therapeutics + Community Advisory Board (PAC model); SF Bay; warm via Sarika | AE78: High | AF78: New | AG78: Not started | AH78: Sarika Agrawal (Co-founder & Board); Pres. Pramila Srinivasan (Purdue PhD)
A79: F075 | B79: SPARK for Autism (SFARI) — data + recruitment | C79: Simons Foundation / SFARI | D79: Philanthropic | E79: Research infrastructure | F79: in-kind | G79: Partner-only | H79: US | I79: PASS | J79: 2 | K79: 5 | L79: 5 | M79: 3 | N79: =ROUND(K79/5*3+L79/5*2.5+J79/5*2+M79/5*2.5,1) -> 7.8 | R79: =IF(Q79="","(n/a)",IF(Q79<=250000,"Small",IF(Q79<=1500000,"Medium",IF(Q79<=10000000,"Large","Mega")))) -> (n/a) | S79: Rolling | T79: SFARI Base apps rolling | U79: Rolling | V79: SFARI Base app (needs institutional affiliation) | W79: peer_review | X79: 2 | Y79: SFARI New Ideas; BRAIN Foundation | Z79: — | AA79: https://sparkforautism.org/portal/page/spark-research-match/ | AB79: https://www.sfari.org/resource/spark/ | AC79: HTML | AD79: 157K+ autistic participants for Yar recruitment + Community Advisory Council = PAC model; $0 but high strategic value | AE79: High | AF79: New | AG79: Not started | AH79: —
A80: F076 | B80: SPARK NS — translational neuroscience accelerator | C80: SPARK NS | D80: Philanthropic | E80: Accelerator / milestone grant | F80: grant | G80: No (academic PI; therapeutics) | H80: US/Intl | I80: BACKUP | J80: 1 | K80: 4 | L80: 4 | M80: 2 | N80: =ROUND(K80/5*3+L80/5*2.5+J80/5*2+M80/5*2.5,1) -> 5.8 | P80: 2000000 | Q80: 2000000 | R80: =IF(Q80="","(n/a)",IF(Q80<=250000,"Small",IF(Q80<=1500000,"Medium",IF(Q80<=10000000,"Large","Mega")))) -> Large | S80: Open | T80: Deadline 2026-06-05 | U80: Recurring | V80: 2yr milestone-based; academic accounts | W80: expert_committee | X80: Backup | Y80: — | Z80: — | AA80: https://sparkns.org/call-for-proposals/ | AB80: https://sparkns.org/ | AC80: HTML | AD80: Therapeutics-only + academic-PI-only; not a platform/AI fit | AE80: High | AF80: New | AG80: Not started | AH80: —
A81: F077 | B81: Autism Society (national) + SFASA (SF Bay affiliate) | C81: Autism Society of America | D81: Mental-Health Foundation | E81: Advocacy / partnership | F81: in-kind | G81: Partner-only (no grants) | H81: US (SF Bay affiliate) | I81: BACKUP | J81: 0 | K81: 5 | L81: 5 | M81: 2 | N81: =ROUND(K81/5*3+L81/5*2.5+J81/5*2+M81/5*2.5,1) -> 6.5 | R81: =IF(Q81="","(n/a)",IF(Q81<=250000,"Small",IF(Q81<=1500000,"Medium",IF(Q81<=10000000,"Large","Mega")))) -> (n/a) | S81: Rolling | T81: Rolling (corporate partnership) | U81: Rolling | V81: Partnership / community channel | W81: internal_panel | X81: Backup | Y81: BRAIN Foundation | Z81: Sarika Agrawal (SFASA Board) — WARM | AA81: https://autismsociety.org/corporate-partnerships/ | AB81: https://autismsociety.org/ | AC81: Newsletter | AD81: No $ but high PAC/partnership + Yar recruitment via SFASA | AE81: High | AF81: New | AG81: Not started | AH81: Sarika Agrawal (SFASA Board) — WARM
A82: F078 | B82: Mental Research Institute (MRI.org) — Research Grants | C82: Mental Research Institute | D82: Mental-Health Foundation | E82: Small grant | F82: grant | G82: Yes (501c3 or fiscal sponsor) | H82: US (SF Bay — Menlo Park) | I82: PASS | J82: 1 | K82: 4 | L82: 3 | M82: 4 | N82: =ROUND(K82/5*3+L82/5*2.5+J82/5*2+M82/5*2.5,1) -> 6.3 | P82: 25000 | Q82: 25000 | R82: =IF(Q82="","(n/a)",IF(Q82<=250000,"Small",IF(Q82<=1500000,"Medium",IF(Q82<=10000000,"Large","Mega")))) -> Small | S82: Rolling | T82: Reviewed monthly (2-phase) | U82: Rolling | V82: Phase1 (~4wk)→Phase2 (~2wk) | W82: internal_panel | X82: 2 | Y82: — | Z82: Bay-Area; office next to PI's therapist | AA82: https://mri.org/apply | AB82: https://mri.org/apply | AC82: HTML | AD82: Tiny ($25K) interactional-systems focus; low-effort Bay-Area bridge; 501c3-eligible (rare) | AE82: High | AF82: New | AG82: Not started | AH82: Bay-Area; near PI's therapist
A83: F079 | B83: Center for Digital Mental Health (MGH / Mass General Brigham) | C83: Massachusetts General Hospital | D83: Academic Center | E83: Research partnership | F83: in-kind | G83: Partner-only | H83: US (Boston) | I83: BACKUP | J83: 5 | K83: 5 | L83: 4 | M83: 2 | N83: =ROUND(K83/5*3+L83/5*2.5+J83/5*2+M83/5*2.5,1) -> 8 | R83: =IF(Q83="","(n/a)",IF(Q83<=250000,"Small",IF(Q83<=1500000,"Medium",IF(Q83<=10000000,"Large","Mega")))) -> (n/a) | S83: Rolling | T83: Consultation/partnership rolling | U83: Rolling | V83: Request consultation / MOU | W83: internal_panel | X83: Backup | Y83: MGH Smoller center | Z83: Jordan Smoller (MGH) adjacency; Manolis↔Smoller; co-advised postdoc | AA83: https://centerfordigitalmentalhealth.org/request-a-consultation/ | AB83: https://centerfordigitalmentalhealth.org/ | AC83: Manual | AD83: AI passive-sensing/wearables/EMA + responsible-AI lived-experience co-design = validator + PAC model (Dir. S. Wilhelm) | AE83: High | AF83: New | AG83: Not started | AH83: Jordan Smoller (MGH) adjacency; Manolis↔Smoller; co-advised postdoc
A84: F080 | B84: APA App Evaluation Model / App Advisor | C84: American Psychiatric Association | D84: Mental-Health Foundation | E84: Endorsement / adoption pathway | F84: in-kind | G84: Yes (any MH tech) | H84: US | I84: PASS | J84: 2 | K84: 5 | L84: 3 | M84: 4 | N84: =ROUND(K84/5*3+L84/5*2.5+J84/5*2+M84/5*2.5,1) -> 7.3 | R84: =IF(Q84="","(n/a)",IF(Q84<=250000,"Small",IF(Q84<=1500000,"Medium",IF(Q84<=10000000,"Large","Mega")))) -> (n/a) | S84: Rolling | T84: Ongoing (updated ~annually) | U84: Rolling | V84: Self-apply framework; seek 'reviewed' status | W84: expert_committee | X84: 2 | Y84: APA Council; SMI Adviser | Z84: — | AA84: https://www.psychiatry.org/psychiatrists/practice/mental-health-apps/the-app-evaluation-model | AB84: https://www.psychiatry.org/psychiatrists/practice/mental-health-apps | AC84: HTML | AD84: Clinical-adoption legitimacy for Yar/Cytonome (NYC DOH, Kaiser, VA use it) | AE84: High | AF84: New | AG84: Not started | AH84: —
A85: F081 | B85: APA Council on Digital Health, Innovation & Technology | C85: American Psychiatric Association | D85: Mental-Health Foundation | E85: Advisory engagement | F85: in-kind | G85: Partner (members-only) | H85: US | I85: BACKUP | J85: 3 | K85: 5 | L85: 3 | M85: 2 | N85: =ROUND(K85/5*3+L85/5*2.5+J85/5*2+M85/5*2.5,1) -> 6.7 | R85: =IF(Q85="","(n/a)",IF(Q85<=250000,"Small",IF(Q85<=1500000,"Medium",IF(Q85<=10000000,"Large","Mega")))) -> (n/a) | S85: Watch | T85: Appointment cycle ~Aug | U85: Recurring | V85: Engage via partnership / app evaluation | W85: internal_panel | X85: Backup | Y85: APA App Evaluation; DSM | Z85: Smoller (APA-adjacent) could ID chair | AA85: https://www.psychiatry.org/about-apa/meet-our-organization/councils/digital-health-innovation-and-technology | AB85: https://www.psychiatry.org/about-apa/meet-our-organization/councils/digital-health-innovation-and-technology | AC85: HTML | AD85: Policy credibility + clinical network for digital psychiatry | AE85: Med | AF85: New | AG85: Not started | AH85: Smoller (APA-adjacent) could ID chair
A86: F082 | B86: APA — Future DSM Strategic Committee (Biomarkers/Dimensions) | C86: American Psychiatric Association | D86: Mental-Health Foundation | E86: Strategic influence | F86: in-kind | G86: Partner (evidence via journals/meeting) | H86: US | I86: PASS | J86: 3 | K86: 5 | L86: 5 | M86: 2 | N86: =ROUND(K86/5*3+L86/5*2.5+J86/5*2+M86/5*2.5,1) -> 7.7 | R86: =IF(Q86="","(n/a)",IF(Q86<=250000,"Small",IF(Q86<=1500000,"Medium",IF(Q86<=10000000,"Large","Mega")))) -> (n/a) | S86: Watch | T86: Active since 2024; no pub timeline | U86: Rolling | V86: Publish in AJP; present at APA; feed Biomarkers subcmte | W86: expert_committee | X86: 3 | Y86: RDoC/HiTOP; Cytoverse | Z86: Dost Öngür (McLean, Dimensions); Maria Oquendo (chair) | AA86: https://psychiatryonline.org/doi/10.1176/appi.ajp.20250877 | AB86: https://www.psychiatry.org | AC86: HTML | AD86: Long-game path to complement/modernize DSM; Biomarkers subcmte accepts external evidence | AE86: Med | AF86: New | AG86: Not started | AH86: Dost Öngür (McLean, Dimensions); publish in AJP
A87: F083 | B87: APA Foundation — O'Leary Award for Innovation | C87: American Psychiatric Association Foundation | D87: Mental-Health Foundation | E87: Award (seed) | F87: grant | G87: Partial (psychiatrist PI) | H87: US | I87: BACKUP | J87: 2 | K87: 5 | L87: 3 | M87: 3 | N87: =ROUND(K87/5*3+L87/5*2.5+J87/5*2+M87/5*2.5,1) -> 6.8 | R87: =IF(Q87="","(n/a)",IF(Q87<=250000,"Small",IF(Q87<=1500000,"Medium",IF(Q87<=10000000,"Large","Mega")))) -> (n/a) | S87: Watch | T87: Annual (2025 closed; next TBD) | U87: Recurring | V87: Nomination→review | W87: expert_committee | X87: Backup | Y87: APA Council | Z87: — | AA87: https://www.psychiatry.org/Membership/Awards-Leadership-Opportunities/Awards/OLeary-Award-for-Innovation-in-Psychiatry | AB87: https://www.psychiatry.org | AC87: HTML | AD87: Seed + APA brand; needs psychiatrist collaborator | AE87: Med | AF87: New | AG87: Not started | AH87: Needs psychiatrist collaborator
A88: F084 | B88: American Psychological Association — APA Labs badge | C88: American Psychological Association | D88: Mental-Health Foundation | E88: Endorsement | F88: in-kind | G88: Yes (MH tools) | H88: US | I88: PASS | J88: 3 | K88: 4 | L88: 3 | M88: 4 | N88: =ROUND(K88/5*3+L88/5*2.5+J88/5*2+M88/5*2.5,1) -> 7.1 | R88: =IF(Q88="","(n/a)",IF(Q88<=250000,"Small",IF(Q88<=1500000,"Medium",IF(Q88<=10000000,"Large","Mega")))) -> (n/a) | S88: Rolling | T88: Open submission (since Aug 2025) | U88: Rolling | V88: Submit tool for evaluation/badge | W88: expert_committee | X88: 2 | Y88: APA (psychiatric) App Eval | Z88: — | AA88: https://www.apa.org | AB88: https://www.apa.org | AC88: HTML | AD88: Parallel endorsement pathway for Yar/Cytonome | AE88: Med | AF88: New | AG88: Not started | AH88: —
A89: F085 | B89: Y Combinator | C89: Y Combinator | D89: Venture Capital | E89: Accelerator + investment | F89: investment | G89: No (equity; PBC) | H89: US | I89: BACKUP | J89: 4 | K89: 4 | L89: 1 | M89: 2 | N89: =ROUND(K89/5*3+L89/5*2.5+J89/5*2+M89/5*2.5,1) -> 5.5 | O89: 125000 | P89: 500000 | Q89: 500000 | R89: =IF(Q89="","(n/a)",IF(Q89<=250000,"Small",IF(Q89<=1500000,"Medium",IF(Q89<=10000000,"Large","Mega")))) -> Medium | S89: Closed-next | T89: Rejected W2025 & Sp2026; Su2026 draft (overdue) | U89: Recurring | V89: Apply→interview | W89: due_diligence | X89: Backup | Y89: — | Z89: Yar-as-PBC wedge | AA89: https://ycombinator.com/apply | AB89: https://ycombinator.com/apply | AC89: HTML | AD89: Nonprofit track narrow; reapply only with traction (Yar PBC) | AE89: High | AF89: Refresh | AG89: Rejected W2025 & Sp2026; Su2026 draft overdue | AH89: Reapply only with traction (Yar PBC)
A90: F086 | B90: Foresight Institute — AI for Science & Safety Nodes | C90: Foresight Institute | D90: EA / Longtermist | E90: Grant + node | F90: grant | G90: Yes | H90: US (SF/Berlin node) | I90: PASS | J90: 4 | K90: 3 | L90: 4 | M90: 4 | N90: =ROUND(K90/5*3+L90/5*2.5+J90/5*2+M90/5*2.5,1) -> 7.4 | O90: 10000 | P90: 100000 | Q90: 50000 | R90: =IF(Q90="","(n/a)",IF(Q90<=250000,"Small",IF(Q90<=1500000,"Medium",IF(Q90<=10000000,"Large","Mega")))) -> Small | S90: Watch | T90: Rolling; reapply with reframe | U90: Rolling | V90: Application form; node participation favored | W90: program-officer | X90: 2 | Y90: EA Funds; SFF | Z90: — | AA90: https://foresight.org/grants/grants-ai-for-science-safety/ | AB90: https://foresight.org/grants/grants-ai-for-science-safety/ | AC90: HTML | AD90: Rejected once (framed as digital health); reframe to cognitive-liberty/BCI/AI-safety per prior plan | AE90: High | AF90: Refresh | AG90: Applied — rejected once | AH90: Reframe to cognitive-liberty/BCI/AI-safety (prior plan)
A91: F087 | B91: QB3 / Bakar Labs (UC Berkeley) | C91: QB3 / UC Berkeley | D91: Corporate | E91: Incubator | F91: in-kind | G91: Path-via-PBC | H91: US (SF Bay) | I91: BACKUP | J91: 2 | K91: 3 | L91: 3 | M91: 2 | N91: =ROUND(K91/5*3+L91/5*2.5+J91/5*2+M91/5*2.5,1) -> 5.1 | R91: =IF(Q91="","(n/a)",IF(Q91<=250000,"Small",IF(Q91<=1500000,"Medium",IF(Q91<=10000000,"Large","Mega")))) -> (n/a) | S91: Closed-next | T91: Applied — rejected | U91: Rolling | V91: Application; wet-lab incubator | W91: internal_panel | X91: Backup | Y91: — | Z91: SF Bay | AA91: https://bakarlabs.berkeley.edu/ | AB91: https://bakarlabs.berkeley.edu/ | AC91: HTML | AD91: Wet-lab incubator; weak fit for an AI/data nonprofit; PBC-only | AE91: High | AF91: Refresh | AG91: Applied — rejected | AH91: SF Bay; PBC-only
A92: F088 | B92: Mount Sinai — Roussos lab / PsychENCODE collaboration | C92: Icahn School of Medicine at Mount Sinai | D92: Academic Center | E92: Research partnership / data | F92: in-kind | G92: Partner-only | H92: US | I92: BACKUP | J92: 3 | K92: 5 | L92: 4 | M92: 3 | N92: =ROUND(K92/5*3+L92/5*2.5+J92/5*2+M92/5*2.5,1) -> 7.7 | R92: =IF(Q92="","(n/a)",IF(Q92<=250000,"Small",IF(Q92<=1500000,"Medium",IF(Q92<=10000000,"Large","Mega")))) -> (n/a) | S92: Rolling | T92: Relationship-based | U92: Rolling | V92: Joint multiscale analysis on PsychENCODE/CMC (Synapse) | W92: peer_review | X92: Backup | Y92: MGH Smoller | Z92: Panos Roussos (Dir. Center for Disease Neurogenomics; PsychENCODE/CommonMind PI) — prior SCZ/BD collaboration | AA92: https://labs.icahn.mssm.edu/roussos-lab/ | AB92: https://icahn.mssm.edu/research/neurogenomics | AC92: Manual | AD92: Cell-type brain omics (SCZ/BD/AD) for Cytoverse micro-meso; open Synapse data | AE92: High | AF92: New | AG92: Not started | AH92: Panos Roussos (Mt Sinai) — prior multi-cohort SCZ/BD collaboration
A93: F089 | B93: MGH — Smoller Center for Precision Psychiatry collaboration | C93: Massachusetts General Hospital | D93: Academic Center | E93: Research partnership / data | F93: in-kind | G93: Partner-only | H93: US | I93: BACKUP | J93: 4 | K93: 5 | L93: 4 | M93: 3 | N93: =ROUND(K93/5*3+L93/5*2.5+J93/5*2+M93/5*2.5,1) -> 8.1 | R93: =IF(Q93="","(n/a)",IF(Q93<=250000,"Small",IF(Q93<=1500000,"Medium",IF(Q93<=10000000,"Large","Mega")))) -> (n/a) | S93: Rolling | T93: Relationship-based | U93: Rolling | V93: Warm intro via Manolis/co-advised postdoc; PGC cross-disorder + EHR | W93: peer_review | X93: Backup | Y93: Mt Sinai Roussos; Center for Digital MH | Z93: Jordan Smoller (Dir.; PGC Cross-Disorder co-chair); Manolis Kellis joint grants; co-advised postdoc | AA93: https://www.massgeneral.org/doctors/17051/jordan-smoller | AB93: https://www.massgeneral.org/psychiatry/research/precision-psychiatry | AC93: Manual | AD93: Cornerstone refs (14-disorder genetics; LLM depression severity); PGC data + co-authorship | AE93: High | AF93: New | AG93: Not started | AH93: Jordan Smoller (MGH) via Manolis Kellis + co-advised postdoc — WARM-ish
A94: F090 | B94: UKRI / MRC — via Manchester (Madhvi Menon, Future Leaders Fellow) | C94: UKRI (MRC/BBSRC/EPSRC) | D94: Government | E94: Research grant | F94: grant | G94: Path-via-partner (UK lead; US = collaborator) | H94: UK | I94: BACKUP | J94: 3 | K94: 4 | L94: 4 | M94: 3 | N94: =ROUND(K94/5*3+L94/5*2.5+J94/5*2+M94/5*2.5,1) -> 7.1 | O94: 500000 | P94: 5000000 | Q94: 2000000 | R94: =IF(Q94="","(n/a)",IF(Q94<=250000,"Small",IF(Q94<=1500000,"Medium",IF(Q94<=10000000,"Large","Mega")))) -> Large | S94: Watch | T94: Leverage Y1-2 (may accelerate) | U94: Recurring | V94: UK PI (Manchester) leads; Cytognosis = international collaborator/project partner | W94: peer_review | X94: 3 | Y94: Horizon; ARIA | Z94: Madhvi Menon (UKRI Future Leaders Fellow, Univ. Manchester) — UK anchor | AA94: https://www.ukri.org/apply-for-funding/ | AB94: https://www.ukri.org/opportunity/ | AC94: HTML | AD94: UK funding via Manchester/Madhvi; US org can't be core-funded but can collaborate; UK entity needed for direct eligibility | AE94: Med | AF94: New | AG94: Planned Y1-2 (may accelerate) | AH94: Madhvi Menon (UKRI Future Leaders Fellow, Univ. Manchester) — UK anchor
A95: F091 | B95: EU — European Partnership for Personalised Medicine (EP PerMed) | C95: European Commission / EP PerMed | D95: Intergovernmental | E95: Consortium grant | F95: grant | G95: Partner (anchor via UK/EU) | H95: EU (US 3rd-country) | I95: BACKUP | J95: 4 | K95: 5 | L95: 5 | M95: 3 | N95: =ROUND(K95/5*3+L95/5*2.5+J95/5*2+M95/5*2.5,1) -> 8.6 | O95: 1000000 | P95: 8000000 | Q95: 3000000 | R95: =IF(Q95="","(n/a)",IF(Q95<=250000,"Small",IF(Q95<=1500000,"Medium",IF(Q95<=10000000,"Large","Mega")))) -> Large | S95: Watch | T95: Annual joint transnational calls (2026 closed Apr 16; next ~2027) | U95: Recurring | V95: Transnational consortium; via Manchester/EU partner | W95: peer_review | X95: 3 | Y95: Horizon Cluster 1 | Z95: Manchester/Madhvi; EU partner institutions | AA95: https://www.epmed.eu/ | AB95: https://www.epmed.eu/ | AC95: HTML | AD95: Personalised-medicine partnership = exact fit; open-science/patient-involvement aligned; anchor via Manchester | AE95: Med | AF95: New | AG95: Not started | AH95: Manchester/Madhvi; EU consortium partner

Sheet Funnel Summary
A1: Funnel Summary & Dashboard
A2: Live counts over the Master sheet (FitScore col N, Wave col X, Bucket col R, Gate col I).
A4: By Wave
A5: Category | B5: Count
A6: Wave 0 — Now (≤4 wks) | B6: =COUNTIF('Master — Funding Opportunities'!$X$5:$X$200,"0") -> 8
A7: Wave 1 — 1–3 months | B7: =COUNTIF('Master — Funding Opportunities'!$X$5:$X$200,"1") -> 12
A8: Wave 2 — 3–6 months | B8: =COUNTIF('Master — Funding Opportunities'!$X$5:$X$200,"2") -> 37
A9: Wave 3 — 6–18 mo / PBC | B9: =COUNTIF('Master — Funding Opportunities'!$X$5:$X$200,"3") -> 17
A10: Backup / Parked | B10: =COUNTIF('Master — Funding Opportunities'!$X$5:$X$200,"Backup") -> 17
A11: TOTAL rows | B11: =COUNTA('Master — Funding Opportunities'!$B$5:$B$200) -> 91
A13: By Funding-Scale Bucket
A14: Category | B14: Count
A15: Small (≤$250K) | B15: =COUNTIF('Master — Funding Opportunities'!$R$5:$R$200,"Small") -> 20
A16: Medium ($250K–1.5M) | B16: =COUNTIF('Master — Funding Opportunities'!$R$5:$R$200,"Medium") -> 23
A17: Large ($1.5–10M) | B17: =COUNTIF('Master — Funding Opportunities'!$R$5:$R$200,"Large") -> 15
A18: Mega (>$10M) | B18: =COUNTIF('Master — Funding Opportunities'!$R$5:$R$200,"Mega") -> 3
A19: Amount not yet verified | B19: =COUNTIF('Master — Funding Opportunities'!$R$5:$R$200,"(n/a)") -> 30
A21: By FitScore band
A22: Category | B22: Count
A23: Strong fit (≥8.0) | B23: =COUNTIF('Master — Funding Opportunities'!$N$5:$N$200,">=8") -> 31
A24: Good fit (6.0–7.9) | B24: =COUNTIFS('Master — Funding Opportunities'!$N$5:$N$200,">=6",'Master — Funding Opportunities'!$N$5:$N$200,"<8") -> 54
A25: Monitor (4.0–5.9) | B25: =COUNTIFS('Master — Funding Opportunities'!$N$5:$N$200,">=4",'Master — Funding Opportunities'!$N$5:$N$200,"<6") -> 6
A26: Deprioritize (<4.0) | B26: =COUNTIFS('Master — Funding Opportunities'!$N$5:$N$200,"<4",'Master — Funding Opportunities'!$N$5:$N$200,">0") -> 0
A28: By L1 Gate
A29: Category | B29: Count
A30: PASS | B30: =COUNTIF('Master — Funding Opportunities'!$I$5:$I$200,"PASS") -> 58
A31: BACKUP | B31: =COUNTIF('Master — Funding Opportunities'!$I$5:$I$200,"BACKUP") -> 33
A32: EXCLUDE | B32: =COUNTIF('Master — Funding Opportunities'!$I$5:$I$200,"EXCLUDE") -> 0
A34: By Source Type
A35: Category | B35: Count
A36: Government | B36: =COUNTIF('Master — Funding Opportunities'!$D$5:$D$200,"Government") -> 20
A37: Philanthropic | B37: =COUNTIF('Master — Funding Opportunities'!$D$5:$D$200,"Philanthropic") -> 23
A38: FRO / Moonshot | B38: =COUNTIF('Master — Funding Opportunities'!$D$5:$D$200,"FRO / Moonshot") -> 7
A39: Corporate | B39: =COUNTIF('Master — Funding Opportunities'!$D$5:$D$200,"Corporate") -> 17
A40: Mental-Health Foundation | B40: =COUNTIF('Master — Funding Opportunities'!$D$5:$D$200,"Mental-Health Foundation") -> 13
A41: EA / Longtermist | B41: =COUNTIF('Master — Funding Opportunities'!$D$5:$D$200,"EA / Longtermist") -> 3
A42: Venture Capital | B42: =COUNTIF('Master — Funding Opportunities'!$D$5:$D$200,"Venture Capital") -> 3
A43: Intergovernmental | B43: =COUNTIF('Master — Funding Opportunities'!$D$5:$D$200,"Intergovernmental") -> 2

Sheet Meta-Sources
A1: Meta-Sources — Discovery & Monitoring Layer
A2: Where opportunities are found / announced. 'Easy' API+RSS rows are the scraper backbone (Stage 2).
A4: ID | B4: Source | C4: Type | D4: Coverage | E4: Free/Paid | F4: Machine-readable feed | G4: Feed / API URL | H4: Update cadence | I4: Scrape feasibility | J4: Priority | K4: Notes (auth / keywords)
A5: S01 | B5: Grants.gov Search2 API | C5: Federal portal | D5: All US federal grants (~26 agencies) | E5: Free, no auth | F5: REST API (JSON, POST) | G5: https://api.grants.gov/v1/api/search2 | H5: Real-time | I5: Easy | J5: High | K5: No key. POST {keyword}. Backbone of scraper. Also RSS GG_NewOppByCategory.xml
A6: S02 | B6: SAM.gov Get Opportunities API v2 | C6: Federal portal | D6: All federal contract/OT/grant opps incl. ARPA-H, NSF X-Labs | E6: Free (API key) | F6: REST API (JSON) | G6: https://api.sam.gov/prod/opportunities/v2/search | H6: Real-time | I6: Easy | J6: High | K6: Register system acct → 1,000 req/day. Filter ptype=g + keywords
A7: S03 | B7: NIH Guide for Grants & Contracts | C7: Federal portal | D7: All NIH FOAs (RFA/PAR/PA/NOT) incl. NIMH/BRAIN | E7: Free | F7: RSS + XML web services | G7: https://grants.nih.gov/grants/guide/newsfeed/fundingopps.xml | H7: Weekly (Fri)+notices | I7: Easy | J7: High | K7: Filter activity code + IC=NIMH + keywords
A8: S04 | B8: NSF Funding Opportunities | C8: Federal portal | D8: All NSF directorates incl. TIP / X-Labs | E8: Free | F8: RSS | G8: https://www.nsf.gov/rss/rss_www_funding_search.xml | H8: Continuous | I8: Easy | J8: High | K8: Keywords: AI, neuroscience, sensing, open science
A9: S05 | B9: Federal Register API | C9: Federal portal | D9: Agency notices, RFIs, program announcements | E9: Free, no auth | F9: REST API (JSON/CSV) | G9: https://www.federalregister.gov/api/v1/documents.json | H9: Daily | I9: Easy | J9: Med | K9: type=NOTICE + term=funding opportunity
A10: S06 | B10: NIH RePORTER API | C10: Federal portal | D10: Funded NIH grants (competitive intel) | E10: Free, no auth | F10: REST API (POST) | G10: https://api.reporter.nih.gov/ | H10: Continuous | I10: Easy | J10: Med | K10: Who funds precision psychiatry — not open opps
A11: S07 | B11: USASpending API | C11: Federal portal | D11: Awarded federal grants/contracts | E11: Free, no auth | F11: REST API | G11: https://api.usaspending.gov/ | H11: Continuous | I11: Easy | J11: Med | K11: Competitive intel on NIH/NSF awards
A12: S08 | B12: ARPA-H Open Funding + Vitals newsletter | C12: Federal portal | D12: ARPA-H ISOs/programs/BAAs | E12: Free | F12: HTML + newsletter | G12: https://arpa-h.gov/explore-funding/open-funding-opportunities | H12: As announced | I12: Hard (use Grants/SAM API) | J12: High | K12: Subscribe Vitals; ARPA-H also posts to Grants.gov/SAM
A13: S09 | B13: EU Funding & Tenders Portal (SEDIA) | C13: Intl portal | D13: Horizon Europe, EIC, ERC, MSCA | E13: Free | F13: REST API + bulk CSV | G13: https://ec.europa.eu/info/funding-tenders/opportunities/data/topic-list.html | H13: Per cycle | I13: Medium | J13: Med | K13: US as consortium partner; keywords health/AI/mental
A14: S10 | B14: UKRI Funding Finder + GtR API | C14: Intl portal | D14: UK research councils + Innovate UK | E14: Free | F14: GtR-2 API (funded) + HTML (open) | G14: https://gtr.ukri.org/api/ | H14: Continuous | I14: Medium | J14: Low-Med | K14: Open calls are HTML scrape; US needs UK partner
A15: S11 | B15: ARIA (UK) funding opportunities | C15: Intl portal | D15: UK ARPA: high-risk programmes + seeds | E15: Free | F15: HTML + email + substack | G15: https://www.aria.org.uk/funding-opportunities/ | H15: Irregular | I15: Hard | J15: Med | K15: Subscribe ariaresearch.substack.com; also UK Find a Grant
... A34: S30 | B34: Hugging Face / Mozilla MOSS / Lambda / Together | C34: Compute rails | D34: Open-model compute + OSS support | E34: Free–credits | F34: HTML/forms | G34: https://huggingface.co/ | H34: Rolling | I34: Easy (apply) | J34: Med | K34: Gemma-class Cytonome inference + OSS support

Sheet PAC & Advocacy
A1: PAC & Advocacy — Companion List
A2: Patient Advocacy Council / partnership targets (separate from funders). OneMind is cross-listed in Master (F019/F051).
A4: ID | B4: Organization | C4: Primary role for Cytognosis | D4: Mission focus | E4: Lived-experience governance | F4: Geography | G4: Engagement / contact path | H4: Also funder/accelerator? | I4: PAC fit (0-10) | J4: Primary URL | K4: Conf.
A5: P01 | B5: OneMind | C5: Dual/tri-use: funder + accelerator + PAC model | D5: MH-broad / severe MH / innovation | E5: Strong — OMLEC council co-reviews grants; OMCAN community network | F5: National (Menlo Park / Napa — Bay-adjacent) | G5: Carmine Di Maro (ED); CSO Tahilia Rebello; engage OMLEC | H5: Yes — Rising Star grants + Accelerator | I5: 9 | J5: https://onemind.org | K5: High
A6: P02 | B6: DBSA (Depression and Bipolar Support Alliance) | C6: PAC seat candidate + model-to-emulate | D6: Mood disorders / peer-run | E6: Strong — chapters peer-run by people with lived experience | F6: National (Chicago HQ; Bay chapters) | G6: dbsalliance.org/contact; invite peer leader to PAC | H6: No | I6: 8 | J6: https://www.dbsalliance.org | K6: High
A7: P03 | B7: Autistic Self Advocacy Network (ASAN) | C7: PAC seat candidate + ND-led model | D7: Neurodivergence / autism / disability rights | E7: Strong — autistic-run; CBPR; 'Nothing About Us, Without Us' | F7: National (DC) | G7: autisticadvocacy.org/about-asan/contact; ND seat | H7: No | I7: 8 | J7: https://autisticadvocacy.org | K7: High
A8: P04 | B8: NAMI San Francisco | C8: PAC seat candidate + Bay-area anchor | D8: MH-broad / BIPOC equity / young adults | E8: Some — Youth Council (lived experience); Diversity cmte | F8: SF Bay Area | G8: aisha@namisf.org (Youth); anne@namisf.org (Diversity) | H8: No | I8: 7 | J8: https://www.namisf.org | K8: High
A9: P05 | B9: Fountain House | C9: Model-to-emulate (member-led research) | D9: Serious mental illness / clubhouse | E9: Strong — RAKE dept runs participatory research WITH members | F9: National (NY; CA Clubhouse Intl affiliates) | G9: fountainhouse.org/contact; CBPR consult; member-researcher seat | H9: No | I9: 7 | J9: https://www.fountainhouse.org | K9: High
A10: P06 | B10: Hopelab | C10: Model-to-emulate + co-research partner | D10: Digital MH / youth / LGBTQ+ / equity | E10: Strong — youth share decision-making incl. strategy/finance | F10: SF Bay Area (San Francisco) | G10: hopelab.org/contact; youth-seat pipeline; co-research | H10: Investor/convener | I10: 7 | J10: https://hopelab.org | K10: High
A11: P07 | B11: NAMI National | C11: Advocacy partner + recruitment channel | D11: MH-broad / SMI / family | E11: Strong — Peer Leadership Council; NAMI Next Gen youth | F11: National (Arlington VA) | G11: partnership@nami.org; MOU for recruitment | H11: No | I11: 6 | J11: https://www.nami.org | K11: High
A12: P08 | B12: Mental Health America (MHA) | C12: Advocacy partner + model (Position Stmt 63) | D12: MH-broad / peer support / policy | E12: Strong — PWLE on board; mandates PWLE on governance | F12: National + 200+ affiliates (CA) | G12: partnerships@mhanational.org; cite Pos. Stmt 63 in PAC charter | H12: Occasional small grants | I12: 6 | J12: https://mhanational.org | K12: High
A13: P09 | B13: Born This Way Foundation | C13: Youth advisory model + advocacy | D13: Youth MH / kindness / LGBTQ+ | E13: Strong — Global Youth Advisory Board co-shapes programs | F13: National (Boston; LA/NYC ops) | G13: bornthisway.foundation/advisory-board-application | H13: No | I13: 6 | J13: https://bornthisway.foundation | K13: High
A14: P10 | B14: Patient-Led Research Collaborative (PLRC) | C14: Governance template for the PAC | D14: Patient-led research governance | E14: Strong — patient-led research org; binding governance model | F14: National / virtual | G14: Study their charter; adapt PAC binding-governance structure | H14: No | I14: 7 | J14: https://patientresearchcovid19.com | K14: Med
A15: P11 | B15: 988 / SPRC Lived Experience Committees | C15: Governance precedent | D15: Suicide prevention / crisis | E15: Strong — formal lived-experience advisory committees | F15: National (federal) | G15: Model binding-council language from their charters | H15: No | I15: 6 | J15: https://988lifeline.org/988lifeline-committees/lived-experience-committee/ | K15: Med
... A30: P26 | B30: Sarika Agrawal (individual connector) | C30: Connector node → BRAIN Foundation + SFASA + autism PAC seats | D30: Autism / NDD (parent-advocate) | E30: n/a (individual) | F30: SF Bay | G30: Send the drafted email (friend of Ananth) | H30: No | I30: — | J30: https://www.linkedin.com/in/sarika-agrawal-573a/ | K30: High

Sheet Wave Action Plan
A1: Wave Action Plan
A2: The single next action per priority target, in time order. Colours match the Master 'Wave' column.
A4: Wave | B4: Window | C4: Opportunity | D4: Single next action | E4: Owner | F4: Hard date / cadence | G4: FitScore ref
A5: 0 | B5: DONE | C5: SAM.gov / Grants.gov registration (UEI/SAM) | D5: ✓ COMPLETE — UEI / SAM.gov account + identifiers already in hand | E5: Ops | F5: Done | G5: prereq
A6: 0 | B6: NOW | C6: Wellcome Leap HBNet | D6: Email HBNet@wellcomeleap.org; sign MARFA/CORFA | E6: PI | F6: This week | G6: F005
A7: 0 | B7: NOW | C7: Convergent Research FRO | D7: Submit 2-3pg Cytoverse FRO abstract | E7: PI | F7: This week (rolling) | G7: F006
A8: 0 | B8: NOW | C8: Anthropic AI for Science / NAIRR / Cohere | D8: Submit credit + compute applications (rolling) | E8: Eng | F8: This week | G8: F007/F008/F017
A9: 0 | B9: ≤1 wk | C9: AWS Imagine Pathfinder | D9: Submit Round-1 application | E9: PI | F9: 2026-06-05 | G9: F003
A10: 0 | B10: ≤2 wk | C10: NIMH BRAIN U01 (RFA-MH-26-140) | D10: Decide go/no-go; line up clinical co-PI; draft | E10: PI | F10: 2026-06-15 | G10: F002
A11: 0 | B11: ≤4 wk | C11: ARPA-H IGoR | D11: Draft + submit Solution Summary | E11: PI | F11: 2026-06-25 | G11: F001
A12: 0 | B12: ≤6 wk | C12: NSF X-Labs Topic 1 (Phase 0) | D12: Finish 8-pg proposal w/ Hervé Marie-Nelly | E12: PI | F12: 2026-07-13 | G12: F004
A13: 1 | B13: 1-3 mo | C13: ARPA-H PHO + HSF ISOs | D13: Submit Solution Summaries (rolling) | E13: PI | F13: June–July | G13: F009/F010
A14: 1 | B14: 1-3 mo | C14: NIMH R21 + R24 + R34 | D14: Pick one; draft for next standard date | E14: PI | F14: Jun 18 / Jun 25 / Oct | G14: F011/F012/F013
A15: 1 | B15: 1-3 mo | C15: Emergent Ventures | D15: Email 1-pg pitch (bridge funding) | E15: PI | F15: Rolling | G15: F014
... A27: 3 | B27: 6-18 mo | C27: EU Horizon Cluster 1 (2027) | D27: Join EU consortium as 3rd-country partner | E27: PI | F27: 2027-02 calls | G27: F053

Sheet Network & Warm-Intro Map
A1: Network & Warm-Intro Map
A2: People -> what they unlock -> warmth -> next action. F-IDs reference the Master sheet. Sensitive ties flagged.
A4: Person | B4: Role / Affiliation | C4: Relationship to Cytognosis | D4: Orgs / Opportunities it unlocks | E4: Warmth | F4: Suggested next action | G4: Conf.
A5: Ananth Grama | B5: Director, Purdue Institute for Physical AI (IPAI); Prof. CS | C5: Cytognosis Board co-chair; PhD advisor; active subaward channel | D5: Eli Lilly LRAP/LPRC/Catalyze360/Ventures; Mayo; Purdue subaward (F066-F068, F072-F073) | E5: Warm | F5: Ask him to broker a Lilly scientist co-sponsor (LRAP) + a Mayo Platform intro | G5: High
A6: Manolis Kellis | B6: Prof., MIT CSAIL / Broad Institute | C6: PI's postdoc advisor; PI = unpaid associated scientist — sensitive dynamics | D6: Jordan Smoller (joint grants); MIT/Broad networks; cross-disorder science | E6: Warm (handle sensitively) | F6: Navigate the dynamic before invoking; leverage via the co-advised postdoc | G6: High
A7: Jordan Smoller | B7: Dir., MGH Center for Precision Psychiatry; co-chair PGC Cross-Disorder Workgroup | C7: Network via Manolis + a co-advised postdoc shadowing bipolar meetings; cornerstone author | D7: MGH precision psychiatry; PGC cross-disorder data; Center for Digital MH adjacency; DSM Biomarkers (F079, F082, F089) | E7: Medium | F7: Warm intro via Manolis/postdoc; explore PGC data + co-authorship | G7: High
A8: Panos Roussos | B8: Dir., Center for Disease Neurogenomics, Mt Sinai; PsychENCODE/CommonMind PI | C8: Prior collaborator on multi-cohort SCZ/BD studies | D8: PsychENCODE/CMC open data (Synapse); Mt Sinai engagement; BD² (F088) | E8: Medium-Warm | F8: Reconnect re: joint multiscale analysis on the PsychENCODE atlases | G8: High
A9: Milad Alucozai | B9: Wyss (Harvard) mentor; GP, Pamir Ventures; ARPA-H Expert-in-Residence | C9: Friend of Ananth; prior outreach email drafted | D9: ARPA-H navigation; Wyss network; advisory/VC (note: Pamir is B2B-AI, not neuro) | E9: Medium | F9: Follow up the prior email; tap ARPA-H/Wyss network + advisory | G9: High
A10: Hani Goodarzi | B10: Core Investigator, Arc Institute (Virtual Cell); Assoc. Prof., UCSF | C10: Same high-school (Iran) tie | D10: Arc Virtual Cell alignment; Arc Alzheimer's Disease Initiative (seeking external collaborators) (F042, F058) | E10: Medium | F10: Reconnect; propose Cytoverse × Arc virtual-cell / AD collaboration | G10: High
A11: Angela Oliveira Pisco | B11: Director of Data Science, Chan Zuckerberg Initiative (CZI); ex-insitro | C11: Former manager at insitro — warm | D11: CZI Science grants; CZI AI/GPU + EOSS; CELLxGENE / cell-atlas co-development (F023, F024) | E11: Warm | F11: Reconnect re: CZI compute/EOSS + the cell-atlas layer of Cytoverse | G11: High
A12: Sarika Agrawal | B12: Co-founder & Board, BRAIN Foundation; Board, Autism Society SF Bay (SFASA) | C12: Friend of Ananth; has an autistic child; prior email drafted | D12: BRAIN Foundation grant; autism advocacy; PAC seats (autism/ND) (F074, F077) | E12: Warm | F12: Send the drafted email; explore BRAIN Foundation + SFASA + PAC seats | G12: High (affiliations verified)
A13: Hervé Marie-Nelly | B13: Founder, stealth co. (ex-insitro colleague) | C13: NSF X-Labs co-submitter | D13: NSF X-Labs Phase 0 (F004) | E13: Warm | F13: Finalize the joint X-Labs proposal (Jul 13) | G13: High
A14: Pramila Srinivasan | B14: President, BRAIN Foundation (Purdue PhD) | C14: Verified Purdue tie at the BRAIN Foundation | D14: BRAIN Foundation (F074) | E14: Medium | F14: Purdue/Ananth-adjacent intro to BRAIN Foundation leadership | G14: Med
A15: Madhvi Menon | B15: UK autoimmune lead, Cytognosis; UKRI Future Leaders Fellow, Univ. of Manchester | C15: Team member — the UK anchor | D15: UKRI/MRC (UK-funded PI route); Horizon Cluster 1 + EP PerMed (UK is Horizon-associated → funded coordinator); possible HBNet route; UK office (F053, F090, F091) | E15: Warm | F15: Map UKRI calls to her FLF; position Manchester as the EU/UK consortium anchor | G15: High
