Workbook

Sheet Summary
A1: IGoR Program — Price Proposal Summary
A2: Cytognosis Foundation (Sub) | IPAI/Purdue (Prime) | ARPA-H Other Transaction
A4: A. Program Totals (All Phases)
A5: Line Item | B5: Amount ($) | C5: Notes
A6: ARPA-H Funds Requested — Phase I (18 mo) | B6: ='By Performer x Phase'!C12 -> 13500000 | C6: Source: IGoR COST_MODEL.md, 2026-06-12
A7: ARPA-H Funds Requested — Phase II (18 mo) | B7: ='By Performer x Phase'!D12 -> 15000000
A8: ARPA-H Funds Requested — Phase III (24 mo) | B8: ='By Performer x Phase'!E12 -> 21500000
A9: ARPA-H Total Requested | B9: ='By Performer x Phase'!F12 -> 50000000 | C9: Must equal $50,000,000
A10: Performer In-Kind Resource Sharing | B10: 4000000 | C10: Illumina BCA data+seq credits; Cellanome instrument; cloud credits
A11: Total Project Value | B11: 54000000 | C11: ARPA-H + in-kind; ~$54M
A13: B. Phase Budget Breakdown
A14: Phase | B14: Duration | C14: ARPA-H Budget ($) | D14: % of Total | E14: Notes
A15: Phase I | B15: 18 months | C15: ='By Performer x Phase'!C12 -> 13500000 | D15: =C15/C18 -> 0.27
A16: Phase II | B16: 18 months | C16: ='By Performer x Phase'!D12 -> 15000000 | D16: =C16/C18 -> 0.3
A17: Phase III | B17: 24 months | C17: ='By Performer x Phase'!E12 -> 21500000 | D17: =C17/C18 -> 0.43
A18: TOTAL | B18: 60 months | C18: =SUM(C15:C17) -> 50000000 | D18: =C18/C18 -> 1
A20: C. Cost Category Summary
A21: Category | B21: Amount ($) | C21: % of Total | D21: Notes
A22: Direct Labor (fully burdened) | B22: 22000000 | C22: =B22/$B$30 -> 0.44 | D22: ~14 FTE/yr blended × 2026 loaded rates
A23: Subcontracts / Consultants | B23: 1000000 | C23: =B23/$B$30 -> 0.02 | D23: Clinical co-lead, biostatistics, ethics/IRB
A24: Materials | B24: 6000000 | C24: =B24/$B$30 -> 0.12 | D24: iPSC, CRISPR libraries, Perturb-seq kits, Cell Painting reagents
A25: Equipment | B25: 2500000 | C25: =B25/$B$30 -> 0.05 | D25: Imaging, instrument access, GPU hardware
A26: Travel | B26: 1000000 | C26: =B26/$B$30 -> 0.02 | D26: DDD workshop, bake-offs, connect-a-thon, IV&V reviews
A27: Other Direct Costs (ODC) | B27: 7000000 | C27: =B27/$B$30 -> 0.14 | D27: GPU/cloud compute, sequencing-as-a-service, storage, licenses
A28: Indirect (F&A / Overhead) | B28: 9000000 | C28: =B28/$B$30 -> 0.18 | D28: Cytognosis 15% de minimis; Purdue ~57% on-campus F&A
A29: Profit / Fee | B29: 1500000 | C29: =B29/$B$30 -> 0.03 | D29: Commercial subs ~7-10%; none for nonprofit/academia
A30: TOTAL | B30: =SUM(B22:B29) -> 50000000 | C30: =B30/B30 -> 1

Sheet By Performer x Phase
A1: By Performer x Phase — ARPA-H Budget Allocation
A3: Performer | B3: Role / TAs | C3: Phase I ($) 18 mo | D3: Phase II ($) 18 mo | E3: Phase III ($) 24 mo | F3: 5-yr Total ($) | G3: Notes
A4: IPAI / Purdue (Prime) | B4: Coordination, PI, Proj Mgmt, Software Architect, TA1/TA2 support | C4: 1900000 | D4: 2100000 | E4: 3000000 | F4: =SUM(C4:E4) -> 7000000 | G4: IPAI prime; Purdue F&A ~57%
A5: Cytognosis (Sub) | B5: TA1 lead, TA2 co-lead | C5: 4000000 | D5: 4200000 | E5: 5800000 | F5: =SUM(C5:E5) -> 14000000 | G5: Cytognosis 15% de minimis MTDC
A6: Phylo (Sub) | B6: TA2 agentic-science partner | C6: 1100000 | D6: 1200000 | E6: 1700000 | F6: =SUM(C6:E6) -> 4000000 | G6: Alt: DataTecnica if Phylo unavailable
A7: SIFT (Sub) | B7: TA3 lead (LabOP / protocol stack) | C7: 1500000 | D7: 1500000 | E7: 2000000 | F7: =SUM(C7:E7) -> 5000000 | G7: Protocol automation + LabOP
A8: Carpenter Lab (Sub) | B8: TA4 lab #1 — optical / Cell Painting | C8: 1300000 | D8: 1500000 | E8: 2200000 | F8: =SUM(C8:E8) -> 5000000 | G8: Broad/JUMP Cell Painting reference data available
A9: Cellanome (Sub) | B9: TA4 lab #2 — live-cell + Perturb-seq | C9: 2000000 | D9: 2400000 | E9: 3600000 | F9: =SUM(C9:E9) -> 8000000 | G9: Also resource-sharing partner
A10: Illumina (Sub) | B10: TA4 lab #3 — sequencing + data | C10: 900000 | D10: 1200000 | E10: 1900000 | F10: =SUM(C10:E10) -> 4000000 | G10: BCA data + seq credits (in-kind ~$2-3M additional)
A11: Cross-team / Reserve | B11: DDD workshop, bake-offs, connect-a-thon, mgmt reserve | C11: 800000 | D11: 900000 | E11: 1300000 | F11: =SUM(C11:E11) -> 3000000 | G11: Integration events + management reserve
A12: GRAND TOTAL | C12: =SUM(C4:C11) -> 13500000 | D12: =SUM(D4:D11) -> 15000000 | E12: =SUM(E4:E11) -> 21500000 | F12: =SUM(F4:F11) -> 50000000 | G12: Must equal $50,000,000
A13: =IF(F12=50000000,"✓ Grand total = $50,000,000","⚠ ERROR: Grand total does not equal $50,000,000") -> ✓ Grand total = $50,000,000
A14: =IF(AND(C12=13500000,D12=15000000,E12=21500000),"✓ Phase totals correct (I=$13.5M, II=$15.0M, III=$21.5M)","⚠ Phase totals mismatch") -> ✓ Phase totals correct (I=$13.5M, II=$15.0M, III=$21.5M)

Sheet Labor
A1: Labor — Direct Labor Cost Detail
A2: Source: IGoR COST_MODEL.md §5, 2026-06-12 | Rates: 2026 fully-loaded (salary+fringe+direct OH)
A4: Labor Category | B4: Organization | C4: FTE (full-time equiv) | D4: Loaded Rate ($/yr) | E4: Annual Hours (est.) | F4: 5-yr Cost ($) | G4: Phase | H4: Basis of Estimate / Notes
A5: CYTOGNOSIS (TA1 Lead + TA2 Co-Lead) — Detailed Breakdown
A6: PI (Mohammadi), partial | B6: Cytognosis | C6: 0.5 | D6: 100000 | E6: =C6*1880 -> 940 | F6: =C6*D6*5 -> 250000 | G6: All phases | H6: Source: COST_MODEL.md §5, 2026-06-12; $200K base × 0.5 FTE loaded
A7: Software Architect (TA2/integ.) | B7: Cytognosis | C7: 1 | D7: 250000 | E7: =C7*1880 -> 1880 | F7: =C7*D7*5 -> 1250000 | G7: All phases | H7: Source: COST_MODEL.md §4, 2026-06-12; Bay Area SW architect blended rate
A8: Senior ML/AI Engineer (TA2) | B8: Cytognosis | C8: 1 | D8: 260000 | E8: =C8*1880 -> 1880 | F8: =C8*D8*5 -> 1300000 | G8: All phases | H8: Source: COST_MODEL.md §4, 2026-06-12; Bay Area ML engineer market rate
A9: ML Research Scientist (TA1/TA2) | B9: Cytognosis | C9: 1 | D9: 240000 | E9: =C9*1880 -> 1880 | F9: =C9*D9*5 -> 1200000 | G9: All phases | H9: Source: COST_MODEL.md §4, 2026-06-12
A10: Computational Biologist (TA1) | B10: Cytognosis | C10: 2 | D10: 210000 | E10: =C10*1880 -> 3760 | F10: =C10*D10*5 -> 2100000 | G10: All phases | H10: Source: COST_MODEL.md §4, 2026-06-12; $210K/FTE × 2 FTE
A11: Technical Project Manager | B11: Cytognosis | C11: 1 | D11: 200000 | E11: =C11*1880 -> 1880 | F11: =C11*D11*5 -> 1000000 | G11: All phases | H11: Source: COST_MODEL.md §4, 2026-06-12
A12: Research Scientist / Postdoc | B12: Cytognosis | C12: 1 | D12: 120000 | E12: =C12*1880 -> 1880 | F12: =C12*D12*5 -> 600000 | G12: All phases | H12: Source: COST_MODEL.md §4, 2026-06-12; industry postdoc rate
A13: Cytognosis Personnel Subtotal | B13: Cytognosis | C13: =SUM(C6:C12) -> 7.5 | D13: =SUMPRODUCT(C6:C12,D6:D12)/SUM(C6:C12) -> 205333.33 | E13: =SUM(E6:E12) -> 14100 | F13: =SUM(F6:F12) -> 7700000
A15: OTHER PERFORMERS — Org-level Summary (detail in individual cost workbooks)
A16: IPAI / Purdue (Prime) | B16: IPAI/Purdue | C16: 3.5 | D16: 140000 | E16: =C16*1880 -> 6580 | F16: =C16*D16*5 -> 2450000 | G16: All phases | H16: PI (Grama) + PM + 1-2 researchers + students; Purdue F&A ~57%
A17: Phylo | B17: Phylo | C17: 2 | D17: 220000 | E17: =C17*1880 -> 3760 | F17: =C17*D17*5 -> 2200000 | G17: All phases | H17: Agentic-science ML engineers; commercial OH embedded in rate
A18: SIFT | B18: SIFT | C18: 3 | D18: 200000 | E18: =C18*1880 -> 5640 | F18: =C18*D18*5 -> 3000000 | G18: All phases | H18: TA3 LabOP / protocol automation engineers
A19: Carpenter Lab | B19: Broad/HMS | C19: 3 | D19: 130000 | E19: =C19*1880 -> 5640 | F19: =C19*D19*5 -> 1950000 | G19: All phases | H19: Academic staff + postdocs; F&A negotiated
A20: Cellanome | B20: Cellanome | C20: 4 | D20: 180000 | E20: =C20*1880 -> 7520 | F20: =C20*D20*5 -> 3600000 | G20: All phases | H20: Lab scientists + bioinformaticians; commercial rate
A21: Illumina | B21: Illumina | C21: 2 | D21: 210000 | E21: =C21*1880 -> 3760 | F21: =C21*D21*5 -> 2100000 | G21: All phases | H21: Data engineers + bioinformatics; commercial rate
A22: PROGRAM LABOR TOTAL (est.) | C22: =SUM(C13,C16:C21) -> 25 | E22: =SUM(E13,E16:E21) -> 47000 | F22: =SUM(F13,F16:F21) -> 23000000
A23: Note: Labor = ~$22.0M of $50.0M total; remaining ~$28.0M covers materials, equipment, travel, ODC, indirect, and fee.

Sheet Equipment
A1: Equipment — ~$2.5M Total
A3: Item Description | B3: Organization | C3: Phase | D3: Qty | E3: Unit Price ($) | F3: Total Price ($) | G3: Vendor/Source | H3: Basis of Estimate
A4: GPU Compute Hardware (on-prem H100 cluster) | B4: Cytognosis | C4: Phase I | D4: 2 | E4: 200000 | F4: =D4*E4 -> 400000 | G4: Various | H4: NVIDIA H100 node; amortized over program; ~$2.50-3.00/GPU-hr alt cloud
A5: Cellanome R3200 Instrument Time (amortized) | B5: Cellanome | C5: All | D5: 1 | E5: 300000 | F5: =D5*E5 -> 300000 | G5: Various | H5: Live-cell imaging; Cellanome partner discount; per COST_MODEL §3
A6: High-content imaging system (Cell Painting) | B6: Carpenter Lab | C6: Phase I | D6: 1 | E6: 250000 | F6: =D6*E6 -> 250000 | G6: Various | H6: Operetta or equivalent; per COST_MODEL §4 optical pooled screen
A7: Liquid handling robotics (TA4 automation) | B7: SIFT | C7: Phase I | D7: 1 | E7: 200000 | F7: =D7*E7 -> 200000 | G7: Various | H7: Hamilton or Tecan; TA3 LabOP protocol stack
A8: Flow cytometry / cell sorter access | B8: Carpenter Lab | C8: Phase II | D8: 1 | E8: 150000 | F8: =D8*E8 -> 150000 | G8: Various | H8: Shared-use instrument; CRO or core facility
A9: Sequencing instruments / flow cell consumables | B9: Illumina | C9: All | D9: 1 | E9: 400000 | F9: =D9*E9 -> 400000 | G9: Various | H9: NovaSeq X; consumables amortized; Illumina partner pricing
A10: Lab computing workstations + storage NAS | B10: IPAI/Purdue | C10: Phase I | D10: 4 | E10: 20000 | F10: =D10*E10 -> 80000 | G10: Various | H10: Scientific workstations; 4 × $20K; standard procurement
A11: Bioreactor / cell culture expansion system | B11: Cellanome | C11: Phase II | D11: 1 | E11: 180000 | F11: =D11*E11 -> 180000 | G11: Various | H11: iPSC expansion; $3-15K/run per COST_MODEL §4
A12: Miscellaneous lab equipment (consumable capital) | B12: Cytognosis | C12: All | D12: 1 | E12: 100000 | F12: =D12*E12 -> 100000 | G12: Various | H12: Pipettes, centrifuges, incubators; standard lab setup
A13: Software licenses (computational biology tools) | B13: Cytognosis | C13: All | D13: 1 | E13: 50000 | F13: =D13*E13 -> 50000 | G13: Various | H13: Schrodinger, GROMACS, domain-specific suites
A14: Reserve / contingency (equipment) | B14: Cross-team | C14: All | D14: 1 | E14: 150000 | F14: =D14*E14 -> 150000 | G14: Various | H14: ~6% reserve on $2.5M equipment budget
A15: TOTAL EQUIPMENT | F15: =SUM(F4:F14) -> 2260000
A16: Target: ~$2.5M | Source: COST_MODEL.md §3, 2026-06-12

Sheet Travel
A1: Travel — ~$1.0M Total
A3: Purpose of Trip | B3: Organization(s) | C3: Phase | D3: Destination | E3: # Travelers | F3: Cost/Traveler ($) | G3: Total ($) | H3: Basis of Estimate
A4: DDD Workshop / Program Kickoff | B4: All performers | C4: Phase I | D4: Washington DC / TBD | E4: 8 | F4: 5000 | G4: =E4*F4 -> 40000 | H4: Annual program-wide meeting; air+hotel+per diem; per COST_MODEL §3
A5: TA3 Bake-off #1 (protocol validation) | B5: SIFT, Cytognosis | C5: Phase I | D5: Remote/TBD | E5: 4 | F5: 3000 | G5: =E5*F5 -> 12000 | H5: TA3 protocol stack evaluation; LabOP standard conformance
A6: TA4 Cross-team Lab Visit (Cell Painting) | B6: Carpenter Lab, Cyto | C6: Phase I | D6: Boston/HMS | E6: 3 | F6: 4000 | G6: =E6*F6 -> 12000 | H6: Wet-lab integration; optical pooled screen setup
A7: Biannual IV&V Review #1 | B7: All performers | C7: Phase I | D7: ARPA-H / DC | E7: 5 | F7: 4500 | G7: =E7*F7 -> 22500 | H7: Defend the Spend; IV&V partner collaboration
A8: Annual Program Meeting (Year 2) | B8: All performers | C8: Phase II | D8: TBD | E8: 8 | F8: 5000 | G8: =E8*F8 -> 40000 | H8: Full team; TA progress review
A9: TA3 Bake-off #2 (cross-team screen) | B9: SIFT, Cellanome | C9: Phase II | D9: TBD | E9: 4 | F9: 3000 | G9: =E9*F9 -> 12000 | H9: Cross-team Perturb-seq / Cell Painting integration
A10: Biannual IV&V Review #2 | B10: All performers | C10: Phase II | D10: ARPA-H / DC | E10: 5 | F10: 4500 | G10: =E10*F10 -> 22500 | H10: Mid-program IV&V
A11: Phase III Connect-a-thon (marketplace) | B11: All performers | C11: Phase III | D11: TBD | E11: 10 | F11: 5000 | G11: =E11*F11 -> 50000 | H11: TA4 marketplace; cross-team + external orgs; per COST_MODEL §3
A12: Dissemination / Conference (ASHG, ISMB, etc. | B12: Cytognosis, Purdue | C12: Phase III | D12: TBD | E12: 4 | F12: 4000 | G12: =E12*F12 -> 16000 | H12: Scientific dissemination; 2 conferences × 4 travelers
A13: Biannual IV&V Reviews #3–#4 | B13: All performers | C13: Phase III | D13: ARPA-H / DC | E13: 5 | F13: 4500 | G13: =E13*F13 -> 22500 | H13: 2 reviews × $22.5K
A14: Travel reserve / contingency | B14: Cross-team | C14: All | D14: Various | E14: 1 | F14: 50000 | G14: =E14*F14 -> 50000 | H14: ~5% reserve on $1.0M travel budget
A15: TOTAL TRAVEL | G15: =SUM(G4:G14) -> 299500
A16: Target: ~$1.0M | Source: COST_MODEL.md §3, 2026-06-12

Sheet ODC
A1: Other Direct Costs (ODC) — ~$7.0M Total
A3: ODC Item | B3: Organization | C3: Phase | D3: Amount ($) | E3: Annualized ($) | F3: Basis of Estimate
A4: GPU/Cloud compute — TA1 FM fine-tuning + causal training | B4: Cytognosis | C4: All | D4: 1250000 | E4: 250000 | F4: ~250-400K/yr × 5 yr; H100 blended ~$2.50-3.00/GPU-hr; COST_MODEL §4
A5: GPU/Cloud compute — TA2 agentic inference + serving | B5: Cytognosis | C5: All | D5: 1000000 | E5: 200000 | F5: ~150-250K/yr × 5 yr; frontier API + open-weight serving; COST_MODEL §4
A6: Sequencing-as-a-service (TA4 scRNA-seq reads) | B6: Cellanome/Illumina | C6: All | D6: 1200000 | E6: 240000 | F6: ~$200-700/sample; ~400 samples/yr; COST_MODEL §4
A7: Cloud storage + data management (Billion Cell Atlas) | B7: Cytognosis | C7: All | D7: 500000 | E7: 100000 | F7: EBS/S3/GCS; ~$100K/yr for multi-TB genomic datasets
A8: Software + API licenses (bioinformatics, LLM APIs) | B8: Cytognosis | C8: All | D8: 400000 | E8: 80000 | F8: Specialized tools, frontier LLM API costs for TA2
A9: Graduate student tuition (Purdue) | B9: Purdue | C9: All | D9: 500000 | E9: 100000 | F9: 2 PhD students × ~$50K tuition/yr × 5 yr; standard Purdue rate
A10: Subcontract admin / consultants (IRB, ethics, standards) | B10: IPAI/Purdue | C10: All | D10: 500000 | E10: 100000 | F10: Clinical co-lead effort, biostatistics, IRB; per COST_MODEL §3
A11: IT/cybersecurity / compliance (OT contractor requirements) | B11: Cross-team | C11: All | D11: 350000 | E11: 70000 | F11: OT CMMC/security compliance for federal work
A12: Publication, data-sharing, open-source release costs | B12: Cytognosis | C12: Phase III | D12: 150000 | E12: 60000 | F12: Apache-2.0 release packaging, preprint fees, data deposit
A13: ODC reserve / contingency | B13: Cross-team | C13: All | D13: 150000 | E13: 30000 | F13: ~2% reserve on $7.0M ODC budget
A14: TOTAL ODC | D14: =SUM(D4:D13) -> 6000000
A15: Target: ~$7.0M | Source: COST_MODEL.md §3-4, 2026-06-12

Sheet Materials
A1: Materials — ~$6.0M Total
A3: Material / Reagent Item | B3: Organization | C3: Phase | D3: Qty (runs/kits/etc.) | E3: Unit Cost ($) | F3: Total ($) | G3: Basis of Estimate
A4: iPSC → NGN2 neuron differentiation (runs) | B4: Cellanome | C4: All | D4: 80 | E4: 9000 | F4: =D4*E4 -> 720000 | G4: ~$3-15K/run mid; NGN2 protocol; COST_MODEL §4
A5: CRISPRi/a guide RNA libraries (genome-scale) | B5: Cellanome | C5: Phase I | D5: 4 | E5: 30000 | F5: =D5*E5 -> 120000 | G5: ~$10-50K/library; Addgene or custom; COST_MODEL §4
A6: Lentivirus production + titering | B6: Cellanome | C6: All | D6: 20 | E6: 15000 | F6: =D6*E6 -> 300000 | G6: ~$10-50K/prep; AAV-free delivery
A7: Targeted Perturb-seq screens (10x Genomics kit) | B7: Cellanome | C7: All | D7: 40 | E7: 15000 | F7: =D7*E7 -> 600000 | G7: ~$5-30K/screen mid; 10x Genomics CRISPR screen kit; COST_MODEL §4
A8: Genome-scale Perturb-seq (full library) | B8: Cellanome | C8: Phase II | D8: 4 | E8: 100000 | F8: =D8*E8 -> 400000 | G8: ~$50-300K/screen; Phase II scale-up
A9: Optical pooled / Cell Painting reagents | B9: Carpenter Lab | C9: All | D9: 10 | E9: 75000 | F9: =D9*E9 -> 750000 | G9: ~$50-500K by scale; mid estimate; COST_MODEL §4
A10: scRNA-seq consumables (samples) | B10: Cellanome/Illumina | C10: All | D10: 1000 | E10: 400 | F10: =D10*E10 -> 400000 | G10: ~$200-700/sample mid; 10x Chromium + NovaSeq flow cells
A11: iPSC cell line acquisition + QC | B11: Cellanome | C11: Phase I | D11: 10 | E11: 8000 | F11: =D11*E11 -> 80000 | G11: Commercial or academic; ~$5-15K/line; QC included
A12: CRISPR editing + validation reagents | B12: Cellanome | C12: All | D12: 1 | E12: 100000 | F12: =D12*E12 -> 100000 | G12: RNPs, HDR templates, sequencing verification; aggregate
A13: Cell culture media + plasticware (consumable) | B13: Carpenter Lab | C13: All | D13: 1 | E13: 200000 | F13: =D13*E13 -> 200000 | G13: Annual consumable budget; TA4 multi-lab
A14: Materials reserve / contingency | B14: Cross-team | C14: All | D14: 1 | E14: 150000 | F14: =D14*E14 -> 150000 | G14: ~2.5% reserve on $6.0M materials budget
A15: TOTAL MATERIALS | F15: =SUM(F4:F14) -> 3820000
A16: Target: ~$6.0M | Source: COST_MODEL.md §3-4, 2026-06-12

Sheet Indirect & Fee
A1: Indirect Costs & Fee — ~$9.0M Indirect + ~$1.5M Fee
A3: INDIRECT COSTS (F&A / Overhead)
A4: Organization | B4: Rate | C4: MTDC Base Est. ($) | D4: Indirect Amount ($) | E4: Phase | F4: Notes / Regulatory Basis
A5: Cytognosis | B5: 0.15 | C5: 10000000 | D5: =B5*C5 -> 1500000 | E5: All | F5: 15% de minimis MTDC; 2 CFR 200.414(f); OT may negotiate actuals
A6: IPAI / Purdue | B6: 0.57 | C6: 5000000 | D6: =B6*C6 -> 2850000 | E6: All | F6: ~57% on-campus F&A; Purdue negotiated rate; COST_MODEL §4
A7: Carpenter Lab | B7: 0.5 | C7: 2000000 | D7: =B7*C7 -> 1000000 | E7: All | F7: HMS/Broad F&A rate (illustrative ~50% on-campus)
A8: SIFT | B8: 0 | C8: 2000000 | D8: =B8*C8 -> 0 | E8: All | F8: Commercial; OH embedded in loaded rate; 0% separate F&A
A9: Phylo | B9: 0 | C9: 1500000 | D9: =B9*C9 -> 0 | E9: All | F9: Commercial; OH embedded in loaded rate
A10: Cellanome | B10: 0 | C10: 4000000 | D10: =B10*C10 -> 0 | E10: All | F10: Commercial; OH embedded in loaded rate
A11: Illumina | B11: 0 | C11: 2000000 | D11: =B11*C11 -> 0 | E11: All | F11: Commercial; OH embedded in loaded rate
A12: TOTAL INDIRECT | C12: =SUM(C5:C11) -> 26500000 | D12: =SUM(D5:D11) -> 5350000
A14: PROFIT / FEE (Commercial Performers Only)
A15: Organization | B15: Fee Rate | C15: Cost Base ($) | D15: Fee Amount ($) | E15: Phase | F15: Notes
A16: Cytognosis | B16: 0 | C16: 14000000 | D16: =B16*C16 -> 0 | E16: All | F16: Nonprofit 501(c)(3); no fee
A17: IPAI / Purdue | B17: 0 | C17: 7000000 | D17: =B17*C17 -> 0 | E17: All | F17: University; no fee
A18: Carpenter Lab | B18: 0 | C18: 5000000 | D18: =B18*C18 -> 0 | E18: All | F18: Academic; no fee
A19: SIFT | B19: 0.08 | C19: 5000000 | D19: =B19*C19 -> 400000 | E19: All | F19: Commercial sub; ~7-10% fee; COST_MODEL §3
A20: Phylo | B20: 0.08 | C20: 4000000 | D20: =B20*C20 -> 320000 | E20: All | F20: Commercial sub; ~7-10% fee
A21: Cellanome | B21: 0.07 | C21: 8000000 | D21: =B21*C21 -> 560000 | E21: All | F21: Commercial sub; ~7% fee; COST_MODEL §3
A22: Illumina | B22: 0.07 | C22: 4000000 | D22: =B22*C22 -> 280000 | E22: All | F22: Commercial sub; ~7% fee
A23: TOTAL FEE | C23: =SUM(C16:C22) -> 47000000 | D23: =SUM(D16:D22) -> 1560000
A25: Note: Indirect ~$9.0M; Fee ~$1.5M. MTDC base excludes subaward amounts above first $50K each (2 CFR 200.331). OT negotiation will finalize actuals.

Sheet Resource Sharing
A1: Performer In-Kind Resource Sharing — ~$4.0M
A2: In-kind not included in $50.0M ARPA-H request; evaluated positively under Criterion 4 | Source: COST_MODEL.md §6, 2026-06-12
A4: Resource Description | B4: Contributing Partner | C4: Type | D4: Estimated Value ($) | E4: Phases Covered | F4: Basis of Estimate
A5: Billion Cell Atlas perturbation data access | B5: Illumina | C5: Data | D5: 1500000 | E5: All phases | F5: BCA multi-TB single-cell perturbation dataset; Illumina partner value; COST_MODEL §6
A6: Illumina sequencing credits (subsidized) | B6: Illumina | C6: Service Credits | D6: 1000000 | E6: All phases | F6: Discounted NovaSeq X flow cells; COST_MODEL §6
A7: Cellanome R3200 instrument access (discount) | B7: Cellanome | C7: Instrument Access | D7: 750000 | E7: All phases | F7: Live-cell single-cell instrument; partner discount vs. list price; COST_MODEL §6
A8: Cloud compute research credits (AWS/GCP) | B8: AWS / GCP | C8: Cloud Credits | D8: 500000 | E8: All phases | F8: Research credit programs; TA1/TA2 GPU workloads; COST_MODEL §6
A9: Broad/JUMP Cell Painting reference data | B9: Broad/JUMP | C9: Data (Open) | D9: 150000 | E9: All phases | F9: Public reference dataset; leverages prior public investment; open access
A10: In-kind contingency / unlisted items | B10: Various | C10: Mixed | D10: 100000 | E10: All phases | F10: Additional resource-sharing items TBD during OT negotiation
A11: TOTAL IN-KIND RESOURCE SHARING | D11: =SUM(D5:D10) -> 4000000
A13: Total project value = ARPA-H $50.0M + in-kind ~$4.0M = ~$54.0M. In-kind is NOT cost-share (not required); it is offered to strengthen Criterion 4 evaluation.
